Workbook

Sheet Read Me
A1: University economics: production backlog (100 videos)
A2: Built 2026-10-22 from open textbooks and the economics channel scan (162 channels, 23,741 videos).
A4: Courses and sources
A5: MI = Intermediate Microeconomics (30): McAfee & Lewis, Introduction to Economic Analysis (CC BY-NC-SA, free PDF).
A6: MA = Intermediate Macroeconomics (26): Garín, Lester & Sims, Intermediate Macroeconomics (free PDF from the authors).
A7: GT = Game Theory (14): Bonanno, Game Theory (open access, UC Davis).
A8: EC = Econometrics (26): Hanck et al., Introduction to Econometrics with R (CC BY-NC-SA); Huntington-Klein, The Effect (free online); Cunningham, Causal Inference: The Mixtape (free online).
A9: XC = cross-course format experiments (4): the full-degree compression, a 5-levels video, a history-of-an-idea video, and the IB diagrams anchor.
A11: Columns
A12: Format: Explainer (model/concept, 8-15 min) / Worked problem ("how to solve X", the format the stale incumbents own) / Anchor ("ALL of…" compression, made after the course's explainers exist).
A13: Exam tag: which exam audiences the topic also serves (IB, A-level, AP) so titles and descriptions can carry the board name; "University" = intermediate-level only.
A14: Demand signal: High = at least 3 small-channel outlier videos (or one at 5x+ its channel) on the raw test AND an age-adjusted signal; Medium = one of the two; Low = comparable videos exist but none outperform; "No comparable video" = nothing in the scan matched.
... A20: Status and Publish date (yellow) are yours to edit; the Progress tab counts them.

Sheet Backlog
A1: Order | B1: Week | C1: Phase | D1: Code | E1: Course | F1: Source section (textbook) | G1: Working title | H1: Format | I1: Target length | J1: Prerequisites | K1: Exam tag | L1: Demand signal | M1: Supply age | N1: Videos found in scan | O1: Channels covering | P1: Small-ch outliers (raw) | Q1: Small-ch outliers (age-adj) | R1: Best small-ch Views/Subs | S1: Best small-ch Views/yr/Subs | T1: Median outlier age (yrs) | U1: Best evidence: video | V1: Evidence channel | W1: Evidence subs | X1: Evidence views | Y1: Views / Subs | Z1: Evidence age (yrs) | AA1: Evidence URL | AB1: Status | AC1: Publish date | AD1: Notes | AE1: Pending rank (helper)
A2: 1 | B2: =ROUNDUP(A2/3,0) -> 1 | C2: Phase 1: intermediate micro + macro, textbook order | D2: MI-01 | E2: Intermediate Microeconomics | F2: McAfee & Lewis, Introduction to Economic Analysis (CC BY-NC-SA) §2 Supply and Demand | G2: Supply and demand, properly: what shifts a curve and what moves along it | H2: Explainer | I2: 8-10 min | J2: None | K2: IB/A-level/AP | L2: High | M2: Stale (median outlier age 8y+) | N2: 71 | O2: 31 | P2: 16 | Q2: 4 | R2: 22.71 | S2: 1.62 | T2: 8 | U2: Supply and Demand (and Equilibrium Price & Quanitity) - Intro to Microeconomics | V2: economicurtis | W2: 36200 | X2: 822000 | Y2: =IF(OR(W2="",W2=0,X2=""),"",X2/W2) -> 22.707182 | Z2: 14 | AA2: https://youtu.be/op70yS_7du8 | AB2: Planned | AE2: =IF(AB2<>"Published",COUNTIF($AB$2:AB2,"<>Published"),"") -> 1
A3: 2 | B3: =ROUNDUP(A3/3,0) -> 1 | C3: Phase 1: intermediate micro + macro, textbook order | D3: MA-01 | E3: Intermediate Macroeconomics | F3: Garín, Lester & Sims, Intermediate Macroeconomics (free PDF) Ch.1-2 Measurement | G3: GDP, properly: three ways to measure one number | H3: Explainer | I3: 8-10 min | J3: None | K3: IB/A-level/AP | L3: High | M3: Ageing (4-8y) | N3: 21 | O3: 15 | P3: 4 | Q3: 0 | R3: 7.22 | S3: 1.61 | T3: 6 | U3: Three methods of GDP Calculation | V3: ecopoint | W3: 29500 | X3: 213000 | Y3: =IF(OR(W3="",W3=0,X3=""),"",X3/W3) -> 7.220339 | Z3: 14 | AA3: https://youtu.be/mgtVQQALWQI | AB3: Planned | AE3: =IF(AB3<>"Published",COUNTIF($AB$2:AB3,"<>Published"),"") -> 2
A4: 3 | B4: =ROUNDUP(A4/3,0) -> 1 | C4: Phase 1: intermediate micro + macro, textbook order | D4: MI-02 | E4: Intermediate Microeconomics | F4: McAfee & Lewis, Introduction to Economic Analysis (CC BY-NC-SA) §2.3 Elasticity | G4: How to solve elasticity problems (point, arc, revenue test) | H4: Worked problem ("how to solve") | I4: 8-10 min | J4: MI-01 | K4: IB/A-level/AP | L4: High | M4: Stale (median outlier age 8y+) | N4: 191 | O4: 38 | P4: 25 | Q4: 6 | R4: 27.88 | S4: 8.12 | T4: 9 | U4: How to Solve Elasticity Problems in Economics | V4: Free Econ Help | W4: 38300 | X4: 603000 | Y4: =IF(OR(W4="",W4=0,X4=""),"",X4/W4) -> 15.744125 | Z4: 15 | AA4: https://youtu.be/-2xh2Fz_XNo | AB4: Planned | AE4: =IF(AB4<>"Published",COUNTIF($AB$2:AB4,"<>Published"),"") -> 3
A5: 4 | B5: =ROUNDUP(A5/3,0) -> 2 | C5: Phase 1: intermediate micro + macro, textbook order | D5: MA-02 | E5: Intermediate Macroeconomics | F5: Garín, Lester & Sims, Intermediate Macroeconomics (free PDF) Ch.2 Prices | G5: Inflation, the CPI and the GDP deflator (and why they disagree) | H5: Explainer | I5: 8-10 min | J5: MA-01 | K5: IB/A-level/AP | L5: High | M5: Stale (median outlier age 8y+) | N5: 64 | O5: 37 | P5: 8 | Q5: 0 | R5: 5.29 | S5: 2.51 | T5: 8 | U5: How to Calculate the Consumer Price Index (CPI) and Inflation Rate | V5: Economics in Many Lessons | W5: 82800 | X5: 400000 | Y5: =IF(OR(W5="",W5=0,X5=""),"",X5/W5) -> 4.8309179 | Z5: 7 | AA5: https://youtu.be/6xJe_oJybDs | AB5: Planned | AE5: =IF(AB5<>"Published",COUNTIF($AB$2:AB5,"<>Published"),"") -> 4
A6: 5 | B6: =ROUNDUP(A6/3,0) -> 2 | C6: Phase 1: intermediate micro + macro, textbook order | D6: MI-03 | E6: Intermediate Microeconomics | F6: McAfee & Lewis, Introduction to Economic Analysis (CC BY-NC-SA) §2.1 Opportunity cost / PPF | G6: How to calculate opportunity cost (and why the PPF is curved) | H6: Worked problem ("how to solve") | I6: 6-8 min | J6: None | K6: IB/A-level/AP | L6: High | M6: Stale (median outlier age 8y+) | N6: 108 | O6: 35 | P6: 25 | Q6: 3 | R6: 23.84 | S6: 2.18 | T6: 10 | U6: How to calculate opportunity costs | V6: Free Econ Help | W6: 38300 | X6: 913000 | Y6: =IF(OR(W6="",W6=0,X6=""),"",X6/W6) -> 23.83812 | Z6: 14 | AA6: https://youtu.be/VZrNbHCkv6A | AB6: Planned | AE6: =IF(AB6<>"Published",COUNTIF($AB$2:AB6,"<>Published"),"") -> 5
A7: 6 | B7: =ROUNDUP(A7/3,0) -> 2 | C7: Phase 1: intermediate micro + macro, textbook order | D7: MA-03 | E7: Intermediate Macroeconomics | F7: Garín, Lester & Sims, Intermediate Macroeconomics (free PDF) Ch.4 Production function | G7: The aggregate production function and diminishing returns to capital | H7: Explainer | I7: 8-10 min | J7: MI-11 | K7: University | L7: Low | M7: - | N7: 6 | O7: 6 | P7: 0 | Q7: 0 | R7: 0.68 | S7: 0.11 | U7: What are diminishing returns in economics | V7: Free Econ Help | W7: 38300 | X7: 26000 | Y7: =IF(OR(W7="",W7=0,X7=""),"",X7/W7) -> 0.67885117 | Z7: 14 | AA7: https://youtu.be/QVlb4ciaKyA | AB7: Planned | AE7: =IF(AB7<>"Published",COUNTIF($AB$2:AB7,"<>Published"),"") -> 6
A8: 7 | B8: =ROUNDUP(A8/3,0) -> 3 | C8: Phase 1: intermediate micro + macro, textbook order | D8: MI-04 | E8: Intermediate Microeconomics | F8: McAfee & Lewis, Introduction to Economic Analysis (CC BY-NC-SA) §2.5 Surplus | G8: Consumer and producer surplus: how to calculate them from a graph | H8: Worked problem ("how to solve") | I8: 6-8 min | J8: MI-01 | K8: IB/A-level/AP | L8: High | M8: Stale (median outlier age 8y+) | N8: 68 | O8: 24 | P8: 14 | Q8: 1 | R8: 13.11 | S8: 1.57 | T8: 12 | U8: How to Calculate Consumer Surplus | V8: Free Econ Help | W8: 38300 | X8: 502000 | Y8: =IF(OR(W8="",W8=0,X8=""),"",X8/W8) -> 13.10705 | Z8: 15 | AA8: https://youtu.be/0hBIwRqTwmY | AB8: Planned | AE8: =IF(AB8<>"Published",COUNTIF($AB$2:AB8,"<>Published"),"") -> 7
A9: 8 | B9: =ROUNDUP(A9/3,0) -> 3 | C9: Phase 1: intermediate micro + macro, textbook order | D9: MA-04 | E9: Intermediate Macroeconomics | F9: Garín, Lester & Sims, Intermediate Macroeconomics (free PDF) Ch.5 Solow model | G9: The Solow growth model, part 1: the diagram and the steady state | H9: Explainer | I9: 12-15 min | J9: MA-03 | K9: University | L9: High | M9: Stale (median outlier age 8y+) | N9: 61 | O9: 12 | P9: 26 | Q9: 3 | R9: 33.53 | S9: 5.59 | T9: 13 | U9: Solow Growth Model | Part 1 | Model Intro & Solution | Intermediate Macroeconomics | V9: Tactical Economics | W9: 3370 | X9: 113000 | Y9: =IF(OR(W9="",W9=0,X9=""),"",X9/W9) -> 33.531157 | Z9: 6 | AA9: https://youtu.be/aywhE3BpJOs | AB9: Planned | AE9: =IF(AB9<>"Published",COUNTIF($AB$2:AB9,"<>Published"),"") -> 8
A10: 9 | B10: =ROUNDUP(A10/3,0) -> 3 | C10: Phase 1: intermediate micro + macro, textbook order | D10: MI-05 | E10: Intermediate Microeconomics | F10: McAfee & Lewis, Introduction to Economic Analysis (CC BY-NC-SA) §5 Government interventions | G10: Price ceilings, floors and taxes: who really pays? | H10: Explainer | I10: 8-10 min | J10: MI-04 | K10: IB/A-level | L10: Medium | M10: Stale (median outlier age 8y+) | N10: 44 | O10: 21 | P10: 5 | Q10: 0 | R10: 3.3 | S10: 0.81 | T10: 8 | U10: Price Ceiling and Price Floor | Think Econ | V10: Think Econ | W10: 77800 | X10: 252000 | Y10: =IF(OR(W10="",W10=0,X10=""),"",X10/W10) -> 3.2390746 | Z10: 4 | AA10: https://youtu.be/a2iKaTqgrxs | AB10: Planned | AE10: =IF(AB10<>"Published",COUNTIF($AB$2:AB10,"<>Published"),"") -> 9
A11: 10 | B11: =ROUNDUP(A11/3,0) -> 4 | C11: Phase 1: intermediate micro + macro, textbook order | D11: MA-05 | E11: Intermediate Macroeconomics | F11: Garín, Lester & Sims, Intermediate Macroeconomics (free PDF) Ch.5-6 Solow extensions | G11: Solow part 2: population, technology and the golden rule | H11: Explainer | I11: 12-15 min | J11: MA-04 | K11: University | L11: High | M11: Stale (median outlier age 8y+) | N11: 14 | O11: 4 | P11: 9 | Q11: 1 | R11: 15.73 | S11: 2.62 | T11: 13 | U11: Solow Growth Model | Part 4 | The Golden Rule | Intermediate Macroeconomics | V11: Tactical Economics | W11: 3370 | X11: 53000 | Y11: =IF(OR(W11="",W11=0,X11=""),"",X11/W11) -> 15.727003 | Z11: 6 | AA11: https://youtu.be/s5PFwvwNKiY | AB11: Planned | AE11: =IF(AB11<>"Published",COUNTIF($AB$2:AB11,"<>Published"),"") -> 10
A12: 11 | B12: =ROUNDUP(A12/3,0) -> 4 | C12: Phase 1: intermediate micro + macro, textbook order | D12: MI-06 | E12: Intermediate Microeconomics | F12: McAfee & Lewis, Introduction to Economic Analysis (CC BY-NC-SA) §12 Consumer Theory: utility | G12: Indifference curves and the budget constraint, visualised | H12: Explainer | I12: 10-12 min | J12: MI-01 | K12: University | L12: High | M12: Stale (median outlier age 8y+) | N12: 107 | O12: 29 | P12: 24 | Q12: 5 | R12: 6.53 | S12: 1.76 | T12: 8 | U12: indifference curves | V12: pajholden | W12: 47500 | X12: 255000 | Y12: =IF(OR(W12="",W12=0,X12=""),"",X12/W12) -> 5.3684211 | Z12: 17 | AA12: https://youtu.be/P_N2hr9aMow | AB12: Planned | AE12: =IF(AB12<>"Published",COUNTIF($AB$2:AB12,"<>Published"),"") -> 11
A13: 12 | B13: =ROUNDUP(A13/3,0) -> 4 | C13: Phase 1: intermediate micro + macro, textbook order | D13: MA-06 | E13: Intermediate Macroeconomics | F13: Garín, Lester & Sims, Intermediate Macroeconomics (free PDF) Ch.7 Growth accounting | G13: Growth accounting: how much of growth is capital, labour and ideas? | H13: Explainer | I13: 8-10 min | J13: MA-05 | K13: University | L13: Low | M13: - | N13: 1 | O13: 1 | P13: 0 | Q13: 0 | R13: 0.53 | S13: 0.18 | U13: Growth Accounting | V13: Klaus Prettner | W13: 8790 | X13: 4700 | Y13: =IF(OR(W13="",W13=0,X13=""),"",X13/W13) -> 0.53469852 | Z13: 3 | AA13: https://youtu.be/GDdM_MWh6xY | AB13: Planned | AE13: =IF(AB13<>"Published",COUNTIF($AB$2:AB13,"<>Published"),"") -> 12
A14: 13 | B14: =ROUNDUP(A14/3,0) -> 5 | C14: Phase 1: intermediate micro + macro, textbook order | D14: MI-07 | E14: Intermediate Microeconomics | F14: McAfee & Lewis, Introduction to Economic Analysis (CC BY-NC-SA) §12.3 Income & substitution effects | G14: Income vs substitution effects (the Slutsky decomposition, step by step) | H14: Explainer | I14: 10-12 min | J14: MI-06 | K14: University | L14: Medium | M14: Stale (median outlier age 8y+) | N14: 44 | O14: 16 | P14: 10 | Q14: 1 | R14: 5.11 | S14: 1.31 | T14: 11.5 | U14: Giffen Good Example - Price Change, Income and Substitution Effect - Intro to Microeconomics | V14: economicurtis | W14: 36200 | X14: 168000 | Y14: =IF(OR(W14="",W14=0,X14=""),"",X14/W14) -> 4.640884 | Z14: 14 | AA14: https://youtu.be/VRC-DVqKYCE | AB14: Planned | AE14: =IF(AB14<>"Published",COUNTIF($AB$2:AB14,"<>Published"),"") -> 13
A15: 14 | B15: =ROUNDUP(A15/3,0) -> 5 | C15: Phase 1: intermediate micro + macro, textbook order | D15: MA-07 | E15: Intermediate Macroeconomics | F15: Garín, Lester & Sims, Intermediate Macroeconomics (free PDF) Ch.9 Consumption | G15: Consumption smoothing: the two-period model and permanent income | H15: Explainer | I15: 10-12 min | J15: MI-06 | K15: University | L15: Low | M15: - | N15: 8 | O15: 3 | P15: 0 | Q15: 0 | R15: 0.65 | S15: 0.17 | U15: Two Period Utility Maximization: Introduction to Inter-temporal | V15: BurkeyAcademy | W15: 37100 | X15: 24000 | Y15: =IF(OR(W15="",W15=0,X15=""),"",X15/W15) -> 0.64690027 | Z15: 9 | AA15: https://youtu.be/0bQh3J82edU | AB15: Planned | AE15: =IF(AB15<>"Published",COUNTIF($AB$2:AB15,"<>Published"),"") -> 14
A16: 15 | B16: =ROUNDUP(A16/3,0) -> 5 | C16: Phase 1: intermediate micro + macro, textbook order | D16: MI-29 | E16: Intermediate Microeconomics | F16: McAfee & Lewis, Introduction to Economic Analysis (CC BY-NC-SA) §12.4 Labour supply | G16: The labour-leisure choice: why higher wages don't always mean more work | H16: Explainer | I16: 8-10 min | J16: MI-07 | K16: University | L16: Medium | M16: Stale (median outlier age 8y+) | N16: 7 | O16: 3 | P16: 1 | Q16: 0 | R16: 2.13 | S16: 0.13 | T16: 17 | U16: substitution and income effects on the backward bending supply curve of labour | V16: pajholden | W16: 47500 | X16: 101000 | Y16: =IF(OR(W16="",W16=0,X16=""),"",X16/W16) -> 2.1263158 | Z16: 17 | AA16: https://youtu.be/R-VCNJKsvwg | AB16: Planned | AE16: =IF(AB16<>"Published",COUNTIF($AB$2:AB16,"<>Published"),"") -> 15
A17: 16 | B17: =ROUNDUP(A17/3,0) -> 6 | C17: Phase 1: intermediate micro + macro, textbook order | D17: MA-26 | E17: Intermediate Macroeconomics | F17: Garín, Lester & Sims, Intermediate Macroeconomics (free PDF) Ch.8 Investment | G17: Investment: Tobin's q and the user cost of capital | H17: Explainer | I17: 8-10 min | J17: MA-03 | K17: University | L17: Low | M17: - | N17: 6 | O17: 5 | P17: 0 | Q17: 0 | R17: 0.27 | S17: 0.07 | U17: Change In Investment Demand and the Loanable Funds Market - Intermediate Macroeconomics | V17: economicurtis | W17: 36200 | X17: 9300 | Y17: =IF(OR(W17="",W17=0,X17=""),"",X17/W17) -> 0.25690608 | Z17: 14 | AA17: https://youtu.be/2j780pByEeI | AB17: Planned | AE17: =IF(AB17<>"Published",COUNTIF($AB$2:AB17,"<>Published"),"") -> 16
A18: 17 | B18: =ROUNDUP(A18/3,0) -> 6 | C18: Phase 1: intermediate micro + macro, textbook order | D18: MI-30 | E18: Intermediate Microeconomics | F18: McAfee & Lewis, Introduction to Economic Analysis (CC BY-NC-SA) §12.5 Intertemporal choice | G18: Saving and borrowing: the intertemporal budget constraint | H18: Explainer | I18: 8-10 min | J18: MI-06 | K18: University | L18: Low | M18: - | N18: 4 | O18: 3 | P18: 0 | Q18: 0 | R18: 0.34 | S18: 0.17 | U18: Intertemporal Utility Maximization: Two Period Example Problems | V18: BurkeyAcademy | W18: 37100 | X18: 9700 | Y18: =IF(OR(W18="",W18=0,X18=""),"",X18/W18) -> 0.26145553 | Z18: 9 | AA18: https://youtu.be/jEdU6wizLF0 | AB18: Planned | AE18: =IF(AB18<>"Published",COUNTIF($AB$2:AB18,"<>Published"),"") -> 17
A19: 18 | B19: =ROUNDUP(A19/3,0) -> 6 | C19: Phase 1: intermediate micro + macro, textbook order | D19: MA-08 | E19: Intermediate Macroeconomics | F19: Garín, Lester & Sims, Intermediate Macroeconomics (free PDF) Ch.12 Labour market | G19: Unemployment: natural rate, cyclical and the labour market diagram | H19: Explainer | I19: 8-10 min | J19: MA-01 | K19: IB/A-level/AP | L19: Medium | M19: Ageing (4-8y) | N19: 26 | O19: 18 | P19: 1 | Q19: 0 | R19: 1.11 | S19: 1.77 | T19: 6 | U19: How to Calculate the Unemployment Rate | Macroeconomics | Think Econ | V19: Think Econ | W19: 77800 | X19: 46000 | Y19: =IF(OR(W19="",W19=0,X19=""),"",X19/W19) -> 0.59125964 | Z19: 3 | AA19: https://youtu.be/3FudpA_fCGQ | AB19: Planned | AE19: =IF(AB19<>"Published",COUNTIF($AB$2:AB19,"<>Published"),"") -> 18
A20: 19 | B20: =ROUNDUP(A20/3,0) -> 7 | C20: Phase 1: intermediate micro + macro, textbook order | D20: MI-08 | E20: Intermediate Microeconomics | F20: McAfee & Lewis, Introduction to Economic Analysis (CC BY-NC-SA) §12.1 Marginal utility | G20: Marginal utility and why demand slopes down | H20: Explainer | I20: 6-8 min | J20: MI-06 | K20: IB/A-level | L20: High | M20: Stale (median outlier age 8y+) | N20: 27 | O20: 17 | P20: 7 | Q20: 1 | R20: 14.64 | S20: 1.83 | T20: 12 | U20: Utility & Marginal Utility | V20: Principles of Microeconomics | W20: 11200 | X20: 164000 | Y20: =IF(OR(W20="",W20=0,X20=""),"",X20/W20) -> 14.642857 | Z20: 8 | AA20: https://youtu.be/DRLS86XfHLg | AB20: Planned | AE20: =IF(AB20<>"Published",COUNTIF($AB$2:AB20,"<>Published"),"") -> 19
A21: 20 | B21: =ROUNDUP(A21/3,0) -> 7 | C21: Phase 1: intermediate micro + macro, textbook order | D21: MA-09 | E21: Intermediate Macroeconomics | F21: Garín, Lester & Sims, Intermediate Macroeconomics (free PDF) Ch.15 Money | G21: How banks create money (the balance-sheet version) | H21: Explainer | I21: 8-10 min | J21: None | K21: IB/A-level/AP | L21: Medium | M21: Stale (median outlier age 8y+) | N21: 34 | O21: 23 | P21: 3 | Q21: 0 | R21: 2.18 | S21: 0.45 | T21: 8 | U21: 💲 Money Creation | How does it work? | V21: EconClips | W21: 113000 | X21: 246000 | Y21: =IF(OR(W21="",W21=0,X21=""),"",X21/W21) -> 2.1769912 | Z21: 8 | AA21: https://youtu.be/3zAvyTKj5-0 | AB21: Planned | AE21: =IF(AB21<>"Published",COUNTIF($AB$2:AB21,"<>Published"),"") -> 20
A22: 21 | B22: =ROUNDUP(A22/3,0) -> 7 | C22: Phase 1: intermediate micro + macro, textbook order | D22: MI-09 | E22: Intermediate Microeconomics | F22: McAfee & Lewis, Introduction to Economic Analysis (CC BY-NC-SA) §9 Producer Theory: cost curves | G22: How to calculate marginal, average and total cost (and draw the curves) | H22: Worked problem ("how to solve") | I22: 8-10 min | J22: None | K22: IB/A-level/AP | L22: Medium | M22: Stale (median outlier age 8y+) | N22: 62 | O22: 24 | P22: 11 | Q22: 1 | R22: 10.22 | S22: 1.42 | T22: 14 | U22: How to Calculate Marginal Cost, Average Total Cost, Average Variable Cost, and Average Fixed Cost | V22: economicurtis | W22: 36200 | X22: 370000 | Y22: =IF(OR(W22="",W22=0,X22=""),"",X22/W22) -> 10.220994 | Z22: 14 | AA22: https://youtu.be/3-j-rZ6hz74 | AB22: Planned | AE22: =IF(AB22<>"Published",COUNTIF($AB$2:AB22,"<>Published"),"") -> 21
A23: 22 | B23: =ROUNDUP(A23/3,0) -> 8 | C23: Phase 1: intermediate micro + macro, textbook order | D23: MA-10 | E23: Intermediate Macroeconomics | F23: Garín, Lester & Sims, Intermediate Macroeconomics (free PDF) Ch.16 The IS curve | G23: The IS curve, derived: goods-market equilibrium and the multiplier | H23: Explainer | I23: 10-12 min | J23: MA-07 | K23: University | L23: Medium | M23: Stale (median outlier age 8y+) | N23: 18 | O23: 15 | P23: 4 | Q23: 1 | R23: 8.37 | S23: 1.37 | T23: 8.5 | U23: Macro Problem - Calculate the IS Curve & LM Curve Equations - Equilibrium Interest Rate & Output | V23: economicurtis | W23: 36200 | X23: 303000 | Y23: =IF(OR(W23="",W23=0,X23=""),"",X23/W23) -> 8.3701657 | Z23: 13 | AA23: https://youtu.be/pAX7mR4ii5Y | AB23: Planned | AE23: =IF(AB23<>"Published",COUNTIF($AB$2:AB23,"<>Published"),"") -> 22
A24: 23 | B24: =ROUNDUP(A24/3,0) -> 8 | C24: Phase 1: intermediate micro + macro, textbook order | D24: MI-10 | E24: Intermediate Microeconomics | F24: McAfee & Lewis, Introduction to Economic Analysis (CC BY-NC-SA) §9.3 Returns to scale | G24: Economies of scale and the long-run average cost curve | H24: Explainer | I24: 6-8 min | J24: MI-09 | K24: IB/A-level/AP | L24: High | M24: Stale (median outlier age 8y+) | N24: 45 | O24: 22 | P24: 6 | Q24: 0 | R24: 6.11 | S24: 3.05 | T24: 13 | U24: Long run average total cost curve relating to economies and diseconomies of scale | V24: Free Econ Help | W24: 38300 | X24: 234000 | Y24: =IF(OR(W24="",W24=0,X24=""),"",X24/W24) -> 6.1096606 | Z24: 14 | AA24: https://youtu.be/URIjtaP6SPk | AB24: Planned | AE24: =IF(AB24<>"Published",COUNTIF($AB$2:AB24,"<>Published"),"") -> 23
A25: 24 | B25: =ROUNDUP(A25/3,0) -> 8 | C25: Phase 1: intermediate micro + macro, textbook order | D25: MA-11 | E25: Intermediate Macroeconomics | F25: Garín, Lester & Sims, Intermediate Macroeconomics (free PDF) Ch.17 The LM curve | G25: The LM curve, derived: money-market equilibrium | H25: Explainer | I25: 8-10 min | J25: MA-10 | K25: University | L25: Medium | M25: Stale (median outlier age 8y+) | N25: 5 | O25: 4 | P25: 3 | Q25: 0 | R25: 8.37 | S25: 0.64 | T25: 13 | U25: Macro Problem - Calculate the IS Curve & LM Curve Equations - Equilibrium Interest Rate & Output | V25: economicurtis | W25: 36200 | X25: 303000 | Y25: =IF(OR(W25="",W25=0,X25=""),"",X25/W25) -> 8.3701657 | Z25: 13 | AA25: https://youtu.be/pAX7mR4ii5Y | AB25: Planned | AE25: =IF(AB25<>"Published",COUNTIF($AB$2:AB25,"<>Published"),"") -> 24
A26: 25 | B26: =ROUNDUP(A26/3,0) -> 9 | C26: Phase 2: micro / macro / game theory / econometrics rotation; micro & macro anchors | D26: MI-11 | E26: Intermediate Microeconomics | F26: McAfee & Lewis, Introduction to Economic Analysis (CC BY-NC-SA) §9.1 Production functions | G26: Cobb-Douglas: the production function that runs economics | H26: Explainer | I26: 8-10 min | J26: MI-09 | K26: University | L26: High | M26: Stale (median outlier age 8y+) | N26: 98 | O26: 21 | P26: 12 | Q26: 0 | R26: 9.7 | S26: 4.63 | T26: 12 | U26: Cobb-Douglas Production Function Differentiation Example | V26: economicurtis | W26: 36200 | X26: 351000 | Y26: =IF(OR(W26="",W26=0,X26=""),"",X26/W26) -> 9.6961326 | Z26: 14 | AA26: https://youtu.be/rYsNHYgIUL4 | AB26: Planned | AE26: =IF(AB26<>"Published",COUNTIF($AB$2:AB26,"<>Published"),"") -> 25
A27: 26 | B27: =ROUNDUP(A27/3,0) -> 9 | C27: Phase 2: micro / macro / game theory / econometrics rotation; micro & macro anchors | D27: MA-12 | E27: Intermediate Macroeconomics | F27: Garín, Lester & Sims, Intermediate Macroeconomics (free PDF) Ch.18 IS-LM | G27: The IS-LM model: fiscal and monetary policy in one diagram | H27: Explainer | I27: 12-15 min | J27: MA-11, MA-12 | K27: University | L27: High | M27: Ageing (4-8y) | N27: 29 | O27: 11 | P27: 12 | Q27: 2 | R27: 5.93 | S27: 1.25 | T27: 4.5 | U27: Introduction to IS LM model | V27: Free Econ Help | W27: 38300 | X27: 227000 | Y27: =IF(OR(W27="",W27=0,X27=""),"",X27/W27) -> 5.926893 | Z27: 14 | AA27: https://youtu.be/Q3hoC8lDCBo | AB27: Planned | AE27: =IF(AB27<>"Published",COUNTIF($AB$2:AB27,"<>Published"),"") -> 26
A28: 27 | B28: =ROUNDUP(A28/3,0) -> 9 | C28: Phase 2: micro / macro / game theory / econometrics rotation; micro & macro anchors | D28: GT-01 | E28: Game Theory | F28: Bonanno, Game Theory (open access, UC Davis) Ch.1 Strategic games | G28: Game theory from zero: payoff matrices and dominant strategies | H28: Explainer | I28: 8-10 min | J28: None | K28: IB/University | L28: High | M28: Stale (median outlier age 8y+) | N28: 13 | O28: 11 | P28: 7 | Q28: 2 | R28: 25.65 | S28: 2.36 | T28: 8 | U28: Intro to Game Theory and the Dominant Strategy Equilibrium | V28: The Economics Detective | W28: 34000 | X28: 872000 | Y28: =IF(OR(W28="",W28=0,X28=""),"",X28/W28) -> 25.647059 | Z28: 13 | AA28: https://youtu.be/3Y1WpytiHKE | AB28: Planned | AE28: =IF(AB28<>"Published",COUNTIF($AB$2:AB28,"<>Published"),"") -> 27
A29: 28 | B29: =ROUNDUP(A29/3,0) -> 10 | C29: Phase 2: micro / macro / game theory / econometrics rotation; micro & macro anchors | D29: EC-01 | E29: Econometrics | F29: Hanck et al., Introduction to Econometrics with R (CC BY-NC-SA) Ch.4 Simple regression | G29: Simple linear regression: what OLS actually minimises (and why) | H29: Explainer | I29: 10-12 min | J29: PS-27 (stats lane) | K29: University | L29: High | M29: Stale (median outlier age 8y+) | N29: 24 | O29: 8 | P29: 5 | Q29: 3 | R29: 13.67 | S29: 1.72 | T29: 12 | U29: Econometrics // Lecture 3: OLS and Goodness-Of-Fit (R-Squared) | V29: KeynesAcademy | W29: 28100 | X29: 384000 | Y29: =IF(OR(W29="",W29=0,X29=""),"",X29/W29) -> 13.66548 | Z29: 13 | AA29: https://youtu.be/8tAPsX0YuNE | AB29: Planned | AE29: =IF(AB29<>"Published",COUNTIF($AB$2:AB29,"<>Published"),"") -> 28
A30: 29 | B30: =ROUNDUP(A30/3,0) -> 10 | C30: Phase 2: micro / macro / game theory / econometrics rotation; micro & macro anchors | D30: MI-28 | E30: Intermediate Microeconomics | F30: McAfee & Lewis, Introduction to Economic Analysis (CC BY-NC-SA) (whole) | G30: ALL of Intermediate Microeconomics in 20 minutes | H30: Anchor (ALL of…) | I30: 20 min | J30: MI-01…MI-27 | K30: University | L30: High | M30: Fresh (<4y) | N30: 11 | O30: 5 | P30: 9 | Q30: 8 | R30: 36.21 | S30: 36.21 | T30: 3 | U30: The Entire Economics Degree in 20 Minutes | V30: 20 Minute University | W30: 145000 | X30: 3100000 | Y30: =IF(OR(W30="",W30=0,X30=""),"",X30/W30) -> 21.37931 | Z30: 1 | AA30: https://youtu.be/NngM_qdDMm8 | AB30: Planned | AE30: =IF(AB30<>"Published",COUNTIF($AB$2:AB30,"<>Published"),"") -> 29
... A46: 45 | B46: =ROUNDUP(A46/3,0) -> 15 | C46: Phase 2: micro / macro / game theory / econometrics rotation; micro & macro anchors | D46: GT-05 | E46: Game Theory | F46: Bonanno, Game Theory (open access, UC Davis) Ch.4 Subgame perfection | G46: Subgame perfect equilibrium: the threats that aren't credible | H46: Explainer | I46: 10-12 min | J46: GT-04 | K46: University | L46: Medium | M46: Stale (median outlier age 8y+) | N46: 2 | O46: 2 | P46: 1 | Q46: 0 | R46: 5.21 | S46: 0.4 | T46: 13 | U46: Subgame Perfect Nash Equilibrium | V46: The Economics Detective | W46: 34000 | X46: 177000 | Y46: =IF(OR(W46="",W46=0,X46=""),"",X46/W46) -> 5.2058824 | Z46: 13 | AA46: https://youtu.be/dTTFzBlpdKA | AB46: Planned | AE46: =IF(AB46<>"Published",COUNTIF($AB$2:AB46,"<>Published"),"") -> 45
A47: 46 | B47: =ROUNDUP(A47/3,0) -> 16 | C47: Phase 2: micro / macro / game theory / econometrics rotation; micro & macro anchors | D47: EC-05 | E47: Econometrics | F47: Hanck et al., Introduction to Econometrics with R (CC BY-NC-SA) Ch.6.4 Multicollinearity | G47: Multicollinearity: why your coefficients went crazy | H47: Explainer | I47: 8-10 min | J47: EC-04 | K47: University | L47: Low | M47: - | N47: 2 | O47: 1 | P47: 0 | Q47: 0 | R47: 0.11 | S47: 0.11 | U47: Multicollinearity – Meaning, Types, Causes, Detection (Econometrics) | V47: Mini Sethi | W47: 92800 | X47: 10000 | Y47: =IF(OR(W47="",W47=0,X47=""),"",X47/W47) -> 0.10775862 | Z47: 1 | AA47: https://youtu.be/VQEPk_SIYT0 | AB47: Planned | AE47: =IF(AB47<>"Published",COUNTIF($AB$2:AB47,"<>Published"),"") -> 46
A48: 47 | B48: =ROUNDUP(A48/3,0) -> 16 | C48: Phase 2: micro / macro / game theory / econometrics rotation; micro & macro anchors | D48: MI-16 | E48: Intermediate Microeconomics | F48: McAfee & Lewis, Introduction to Economic Analysis (CC BY-NC-SA) §15.4 Price discrimination | G48: Price discrimination: why the same seat costs three prices | H48: Explainer | I48: 8-10 min | J48: MI-14 | K48: IB/A-level | L48: Medium | M48: Stale (median outlier age 8y+) | N48: 42 | O48: 18 | P48: 4 | Q48: 0 | R48: 7.35 | S48: 0.61 | T48: 13 | U48: Price discrimination | V48: Economics Online | W48: 5990 | X48: 44000 | Y48: =IF(OR(W48="",W48=0,X48=""),"",X48/W48) -> 7.345576 | Z48: 12 | AA48: https://youtu.be/IZ1iAYhQnwg | AB48: Planned | AE48: =IF(AB48<>"Published",COUNTIF($AB$2:AB48,"<>Published"),"") -> 47
A49: 48 | B49: =ROUNDUP(A49/3,0) -> 16 | C49: Phase 2: micro / macro / game theory / econometrics rotation; micro & macro anchors | D49: MA-17 | E49: Intermediate Macroeconomics | F49: Garín, Lester & Sims, Intermediate Macroeconomics (free PDF) Ch.24 Open economy | G49: Exchange rates and the balance of payments, explained | H49: Explainer | I49: 10-12 min | J49: MA-01 | K49: IB/A-level | L49: Medium | M49: Stale (median outlier age 8y+) | N49: 116 | O49: 28 | P49: 11 | Q49: 0 | R49: 3.03 | S49: 0.84 | T49: 8 | U49: balance of payments - structure of the current account | V49: pajholden | W49: 47500 | X49: 144000 | Y49: =IF(OR(W49="",W49=0,X49=""),"",X49/W49) -> 3.0315789 | Z49: 18 | AA49: https://youtu.be/JKRBpJZ92QM | AB49: Planned | AE49: =IF(AB49<>"Published",COUNTIF($AB$2:AB49,"<>Published"),"") -> 48
A50: 49 | B50: =ROUNDUP(A50/3,0) -> 17 | C50: Phase 3: econometrics & game theory heavy; IB anchor; remaining topics | D50: GT-06 | E50: Game Theory | F50: Bonanno, Game Theory (open access, UC Davis) Ch.5 Mixed strategies | G50: Mixed strategies: how to solve for the probabilities | H50: Worked problem ("how to solve") | I50: 10-12 min | J50: GT-02 | K50: University | L50: Medium | M50: Stale (median outlier age 8y+) | N50: 15 | O50: 4 | P50: 6 | Q50: 0 | R50: 3.62 | S50: 0.9 | T50: 13 | U50: Mixed Strategies Nash Equilibrium: The Math | V50: Ashley Hodgson | W50: 55600 | X50: 201000 | Y50: =IF(OR(W50="",W50=0,X50=""),"",X50/W50) -> 3.6151079 | Z50: 4 | AA50: https://youtu.be/S49oKtISkqI | AB50: Planned | AE50: =IF(AB50<>"Published",COUNTIF($AB$2:AB50,"<>Published"),"") -> 49
A51: 50 | B51: =ROUNDUP(A51/3,0) -> 17 | C51: Phase 3: econometrics & game theory heavy; IB anchor; remaining topics | D51: EC-06 | E51: Econometrics | F51: Hanck et al., Introduction to Econometrics with R (CC BY-NC-SA) Ch.5.4 Heteroskedasticity | G51: Heteroskedasticity and robust standard errors | H51: Explainer | I51: 8-10 min | J51: EC-03 | K51: University | L51: Medium | M51: Ageing (4-8y) | N51: 3 | O51: 3 | P51: 1 | Q51: 0 | R51: 2.54 | S51: 0.51 | T51: 5 | U51: Wooldridge Econometrics for Economics BSc students Ch. 8: Heteroskedasticity | V51: youtube-economist | W51: 7880 | X51: 20000 | Y51: =IF(OR(W51="",W51=0,X51=""),"",X51/W51) -> 2.5380711 | Z51: 5 | AA51: https://youtu.be/DMzBRYqAHrE | AB51: Planned | AE51: =IF(AB51<>"Published",COUNTIF($AB$2:AB51,"<>Published"),"") -> 50
A52: 51 | B52: =ROUNDUP(A52/3,0) -> 17 | C52: Phase 3: econometrics & game theory heavy; IB anchor; remaining topics | D52: EC-07 | E52: Econometrics | F52: Hanck et al., Introduction to Econometrics with R (CC BY-NC-SA) Ch.8 Nonlinear | G52: Logs in regression: how to read elasticities and percent changes | H52: Explainer | I52: 8-10 min | J52: EC-04 | K52: University | L52: Medium | M52: Stale (median outlier age 8y+) | N52: 11 | O52: 4 | P52: 4 | Q52: 0 | R52: 4.2 | S52: 0.32 | T52: 13 | U52: Log-Log Regression & Interpretation (What do the Regression Coefficient Estimate Results Mean?) | V52: economicurtis | W52: 36200 | X52: 152000 | Y52: =IF(OR(W52="",W52=0,X52=""),"",X52/W52) -> 4.198895 | Z52: 13 | AA52: https://youtu.be/NZCSt9WkpkI | AB52: Planned | AE52: =IF(AB52<>"Published",COUNTIF($AB$2:AB52,"<>Published"),"") -> 51
A53: 52 | B53: =ROUNDUP(A53/3,0) -> 18 | C53: Phase 3: econometrics & game theory heavy; IB anchor; remaining topics | D53: GT-07 | E53: Game Theory | F53: Bonanno, Game Theory (open access, UC Davis) Ch.7 Repeated games | G53: Repeated games and tit-for-tat: how cooperation survives | H53: Explainer | I53: 10-12 min | J53: GT-03 | K53: University | L53: Low | M53: - | N53: 4 | O53: 4 | P53: 0 | Q53: 0 | R53: 0.86 | S53: 0.22 | U53: Repeated Games in Game Theory | V53: Ashley Hodgson | W53: 55600 | X53: 48000 | Y53: =IF(OR(W53="",W53=0,X53=""),"",X53/W53) -> 0.86330935 | Z53: 4 | AA53: https://youtu.be/A0sR5pz69IE | AB53: Planned | AE53: =IF(AB53<>"Published",COUNTIF($AB$2:AB53,"<>Published"),"") -> 52
A54: 53 | B54: =ROUNDUP(A54/3,0) -> 18 | C54: Phase 3: econometrics & game theory heavy; IB anchor; remaining topics | D54: MI-17 | E54: Intermediate Microeconomics | F54: McAfee & Lewis, Introduction to Economic Analysis (CC BY-NC-SA) §17 Oligopoly: Cournot | G54: How to solve a Cournot oligopoly problem | H54: Worked problem ("how to solve") | I54: 10-12 min | J54: MI-14, GT-01 | K54: University | L54: Medium | M54: Stale (median outlier age 8y+) | N54: 16 | O54: 9 | P54: 4 | Q54: 1 | R54: 8.25 | S54: 1.43 | T54: 11 | U54: How to Solve a Cournot Oligopoly Problem | V54: Economics in Many Lessons | W54: 82800 | X54: 683000 | Y54: =IF(OR(W54="",W54=0,X54=""),"",X54/W54) -> 8.2487923 | Z54: 13 | AA54: https://youtu.be/An_2r6Ae_28 | AB54: Planned | AE54: =IF(AB54<>"Published",COUNTIF($AB$2:AB54,"<>Published"),"") -> 53
A55: 54 | B55: =ROUNDUP(A55/3,0) -> 18 | C55: Phase 3: econometrics & game theory heavy; IB anchor; remaining topics | D55: MA-18 | E55: Intermediate Macroeconomics | F55: Garín, Lester & Sims, Intermediate Macroeconomics (free PDF) Ch.25 Mundell-Fleming | G55: The Mundell-Fleming model: the trilemma every central bank faces | H55: Explainer | I55: 12-15 min | J55: MA-13, MA-18 | K55: University | L55: Medium | M55: Fresh (<4y) | N55: 7 | O55: 6 | P55: 2 | Q55: 1 | R55: 3.07 | S55: 1.54 | T55: 3.5 | U55: The Mundell-Fleming Model by Vidhi Kalra | V55: 5 Minute Economics | W55: 99200 | X55: 167000 | Y55: =IF(OR(W55="",W55=0,X55=""),"",X55/W55) -> 1.6834677 | Z55: 5 | AA55: https://youtu.be/U7K2OTQj4ZQ | AB55: Planned | AE55: =IF(AB55<>"Published",COUNTIF($AB$2:AB55,"<>Published"),"") -> 54
A56: 55 | B56: =ROUNDUP(A56/3,0) -> 19 | C56: Phase 3: econometrics & game theory heavy; IB anchor; remaining topics | D56: EC-08 | E56: Econometrics | F56: Huntington-Klein, The Effect (free online) Ch.5-6 Causality | G56: Correlation vs causation: the DAG way of thinking | H56: Explainer | I56: 10-12 min | J56: EC-04 | K56: University | L56: Low | M56: - | N56: 5 | O56: 4 | P56: 0 | Q56: 0 | R56: 0.38 | S56: 0.08 | U56: Data Science Research Methods: Causality and selection | V56: youtube-economist | W56: 7880 | X56: 3000 | Y56: =IF(OR(W56="",W56=0,X56=""),"",X56/W56) -> 0.38071066 | Z56: 5 | AA56: https://youtu.be/oJgGuRG_lNY | AB56: Planned | AE56: =IF(AB56<>"Published",COUNTIF($AB$2:AB56,"<>Published"),"") -> 55
A57: 56 | B57: =ROUNDUP(A57/3,0) -> 19 | C57: Phase 3: econometrics & game theory heavy; IB anchor; remaining topics | D57: GT-08 | E57: Game Theory | F57: Bonanno, Game Theory (open access, UC Davis) Ch.8 Bayesian games | G57: Games with incomplete information: Bayesian Nash equilibrium | H57: Explainer | I57: 10-12 min | J57: GT-06 | K57: University | L57: No comparable video | M57: - | N57: 0 | O57: 0 | P57: 0 | Q57: 0 | R57: 0 | S57: 0 | Y57: =IF(OR(W57="",W57=0,X57=""),"",X57/W57) | AB57: Planned | AE57: =IF(AB57<>"Published",COUNTIF($AB$2:AB57,"<>Published"),"") -> 56
A58: 57 | B58: =ROUNDUP(A58/3,0) -> 19 | C58: Phase 3: econometrics & game theory heavy; IB anchor; remaining topics | D58: MI-18 | E58: Intermediate Microeconomics | F58: McAfee & Lewis, Introduction to Economic Analysis (CC BY-NC-SA) §17.2 Stackelberg | G58: How to solve a Stackelberg problem (and why moving first pays) | H58: Worked problem ("how to solve") | I58: 8-10 min | J58: MI-17 | K58: University | L58: Medium | M58: Stale (median outlier age 8y+) | N58: 12 | O58: 7 | P58: 4 | Q58: 1 | R58: 4.95 | S58: 1.43 | T58: 12 | U58: How to Solve A Stackelberg Oligopoly Problem | V58: Economics in Many Lessons | W58: 82800 | X58: 410000 | Y58: =IF(OR(W58="",W58=0,X58=""),"",X58/W58) -> 4.9516908 | Z58: 13 | AA58: https://youtu.be/LMCODkeeDtE | AB58: Planned | AE58: =IF(AB58<>"Published",COUNTIF($AB$2:AB58,"<>Published"),"") -> 57
A59: 58 | B59: =ROUNDUP(A59/3,0) -> 20 | C59: Phase 3: econometrics & game theory heavy; IB anchor; remaining topics | D59: MA-19 | E59: Intermediate Macroeconomics | F59: Garín, Lester & Sims, Intermediate Macroeconomics (free PDF) Ch.26 Financial crises | G59: Bank runs and financial crises: the Diamond-Dybvig idea | H59: Explainer | I59: 10-12 min | J59: MA-09 | K59: University | L59: Medium | M59: Fresh (<4y) | N59: 18 | O59: 15 | P59: 1 | Q59: 0 | R59: 1.36 | S59: 0.52 | T59: 0.2 | U59: ALL OF The 2008 Financial Crisis Explained in 43 Minutes | V59: Fred - Money Historian | W59: 12500 | X59: 17000 | Y59: =IF(OR(W59="",W59=0,X59=""),"",X59/W59) -> 1.36 | Z59: 0.25 | AA59: https://youtu.be/L6KmmdVISj4 | AB59: Planned | AE59: =IF(AB59<>"Published",COUNTIF($AB$2:AB59,"<>Published"),"") -> 58
A60: 59 | B60: =ROUNDUP(A60/3,0) -> 20 | C60: Phase 3: econometrics & game theory heavy; IB anchor; remaining topics | D60: EC-09 | E60: Econometrics | F60: Cunningham, Causal Inference: The Mixtape (free online) Ch.4 Potential outcomes | G60: Potential outcomes and the randomised experiment: the gold standard | H60: Explainer | I60: 10-12 min | J60: EC-08 | K60: University | L60: Medium | M60: Stale (median outlier age 8y+) | N60: 7 | O60: 6 | P60: 1 | Q60: 0 | R60: 3.17 | S60: 0.35 | T60: 9 | U60: The problems with Randomised Controlled Trials | V60: CEPR & VideoVox Economics | W60: 10400 | X60: 33000 | Y60: =IF(OR(W60="",W60=0,X60=""),"",X60/W60) -> 3.1730769 | Z60: 9 | AA60: https://youtu.be/UB1A62u9fBE | AB60: Planned | AE60: =IF(AB60<>"Published",COUNTIF($AB$2:AB60,"<>Published"),"") -> 59
A61: 60 | B61: =ROUNDUP(A61/3,0) -> 20 | C61: Phase 3: econometrics & game theory heavy; IB anchor; remaining topics | D61: GT-09 | E61: Game Theory | F61: Bonanno, Game Theory (open access, UC Davis) Ch.9 Signalling | G61: Signalling games: why degrees exist (Spence) | H61: Explainer | I61: 10-12 min | J61: GT-08 | K61: University | L61: Low | M61: - | N61: 7 | O61: 6 | P61: 0 | Q61: 0 | R61: 0.13 | S61: 0.01 | U61: The Signalling Model of Education | V61: The Economics Detective | W61: 34000 | X61: 4300 | Y61: =IF(OR(W61="",W61=0,X61=""),"",X61/W61) -> 0.12647059 | Z61: 9 | AA61: https://youtu.be/g35WfYYFKRc | AB61: Planned | AE61: =IF(AB61<>"Published",COUNTIF($AB$2:AB61,"<>Published"),"") -> 60
A62: 61 | B62: =ROUNDUP(A62/3,0) -> 21 | C62: Phase 3: econometrics & game theory heavy; IB anchor; remaining topics | D62: MI-19 | E62: Intermediate Microeconomics | F62: McAfee & Lewis, Introduction to Economic Analysis (CC BY-NC-SA) §17.3 Bertrand | G62: Bertrand competition: why two firms can be enough for competitive prices | H62: Explainer | I62: 8-10 min | J62: MI-17 | K62: University | L62: Medium | M62: Stale (median outlier age 8y+) | N62: 13 | O62: 9 | P62: 5 | Q62: 1 | R62: 2.86 | S62: 1.43 | T62: 11 | U62: Oligopoly: Bertrand Competition with Differentiated Goods | V62: Economics in Many Lessons | W62: 82800 | X62: 210000 | Y62: =IF(OR(W62="",W62=0,X62=""),"",X62/W62) -> 2.5362319 | Z62: 13 | AA62: https://youtu.be/YrnqUPW96lY | AB62: Planned | AE62: =IF(AB62<>"Published",COUNTIF($AB$2:AB62,"<>Published"),"") -> 61
A63: 62 | B63: =ROUNDUP(A63/3,0) -> 21 | C63: Phase 3: econometrics & game theory heavy; IB anchor; remaining topics | D63: MA-20 | E63: Intermediate Macroeconomics | F63: Garín, Lester & Sims, Intermediate Macroeconomics (free PDF) Ch.14 Classical vs Keynesian | G63: Classical vs Keynesian: what they actually disagree about | H63: Explainer | I63: 10-12 min | J63: MA-14 | K63: IB/A-level/AP | L63: High | M63: Stale (median outlier age 8y+) | N63: 2 | O63: 2 | P63: 1 | Q63: 0 | R63: 6.14 | S63: 1.71 | T63: 9 | U63: Macro: Unit 2.6 -- Classical v. Keynesian Theories | V63: You Will Love Economics | W63: 77900 | X63: 478000 | Y63: =IF(OR(W63="",W63=0,X63=""),"",X63/W63) -> 6.1360719 | Z63: 9 | AA63: https://youtu.be/xXNrloLHOzI | AB63: Planned | AE63: =IF(AB63<>"Published",COUNTIF($AB$2:AB63,"<>Published"),"") -> 62
A64: 63 | B64: =ROUNDUP(A64/3,0) -> 21 | C64: Phase 3: econometrics & game theory heavy; IB anchor; remaining topics | D64: XC-04 | E64: Cross-course | F64: Exam funnel | G64: Every IB Economics diagram in 15 minutes | H64: Anchor (ALL of…) | I64: 15 min | J64: MI-01…MA-18 | K64: IB | L64: High | M64: Stale (median outlier age 8y+) | N64: 289 | O64: 6 | P64: 27 | Q64: 3 | R64: 5.54 | S64: 8.3 | T64: 10 | U64: What is Economic Growth vs. Economic Development? | IB Microeconomics | IB Economics Exam Review | V64: Brad Cartwright | W64: 43300 | X64: 177000 | Y64: =IF(OR(W64="",W64=0,X64=""),"",X64/W64) -> 4.0877598 | Z64: 10 | AA64: https://youtu.be/4D_36i4zVFs | AB64: Planned | AE64: =IF(AB64<>"Published",COUNTIF($AB$2:AB64,"<>Published"),"") -> 63
A65: 64 | B65: =ROUNDUP(A65/3,0) -> 22 | C65: Phase 3: econometrics & game theory heavy; IB anchor; remaining topics | D65: EC-10 | E65: Econometrics | F65: Huntington-Klein, The Effect (free online) Ch.18 Difference-in-differences | G65: Difference-in-differences, intuitively | H65: Explainer | I65: 10-12 min | J65: EC-09 | K65: University | L65: High | M65: Stale (median outlier age 8y+) | N65: 2 | O65: 2 | P65: 1 | Q65: 1 | R65: 49.82 | S65: 4.53 | T65: 11 | U65: An intuitive introduction to Difference-in-Differences | V65: Doug McKee | W65: 5480 | X65: 273000 | Y65: =IF(OR(W65="",W65=0,X65=""),"",X65/W65) -> 49.817518 | Z65: 11 | AA65: https://youtu.be/J7q2H8aB8bQ | AB65: Planned | AE65: =IF(AB65<>"Published",COUNTIF($AB$2:AB65,"<>Published"),"") -> 64
A66: 65 | B66: =ROUNDUP(A66/3,0) -> 22 | C66: Phase 3: econometrics & game theory heavy; IB anchor; remaining topics | D66: GT-10 | E66: Game Theory | F66: Bonanno, Game Theory (open access, UC Davis) Ch.6 Auctions | G66: Auctions: first-price, second-price and why you should bid your value | H66: Explainer | I66: 10-12 min | J66: GT-08 | K66: University | L66: Low | M66: - | N66: 9 | O66: 7 | P66: 0 | Q66: 0 | R66: 0.15 | S66: 0.01 | U66: A problem with auctions - applying consumer surplus | V66: pajholden | W66: 47500 | X66: 7000 | Y66: =IF(OR(W66="",W66=0,X66=""),"",X66/W66) -> 0.14736842 | Z66: 16 | AA66: https://youtu.be/vQgjpRQ5wxI | AB66: Planned | AE66: =IF(AB66<>"Published",COUNTIF($AB$2:AB66,"<>Published"),"") -> 65
A67: 66 | B67: =ROUNDUP(A67/3,0) -> 22 | C67: Phase 3: econometrics & game theory heavy; IB anchor; remaining topics | D67: MI-20 | E67: Intermediate Microeconomics | F67: McAfee & Lewis, Introduction to Economic Analysis (CC BY-NC-SA) §16 Monopolistic competition | G67: Monopolistic competition in the short and long run | H67: Explainer | I67: 8-10 min | J67: MI-14 | K67: IB/A-level/AP | L67: Medium | M67: Ageing (4-8y) | N67: 37 | O67: 22 | P67: 9 | Q67: 1 | R67: 10.85 | S67: 1.46 | T67: 7 | U67: Monopolistic competition | V67: Economics Online | W67: 5990 | X67: 65000 | Y67: =IF(OR(W67="",W67=0,X67=""),"",X67/W67) -> 10.851419 | Z67: 12 | AA67: https://youtu.be/XG6jWY0SvC0 | AB67: Planned | AE67: =IF(AB67<>"Published",COUNTIF($AB$2:AB67,"<>Published"),"") -> 66
A68: 67 | B68: =ROUNDUP(A68/3,0) -> 23 | C68: Phase 3: econometrics & game theory heavy; IB anchor; remaining topics | D68: MA-21 | E68: Intermediate Macroeconomics | F68: Garín, Lester & Sims, Intermediate Macroeconomics (free PDF) Ch.11 Real business cycles | G68: Real business cycle theory: recessions as rational responses? | H68: Explainer | I68: 10-12 min | J68: MA-04 | K68: University | L68: Medium | M68: Ageing (4-8y) | N68: 6 | O68: 4 | P68: 1 | Q68: 0 | R68: 2.84 | S68: 0.71 | T68: 4 | U68: Real-Business-Cycle (RBC) Model Part 1: The Simplest Version of the RBC Model | V68: Klaus Prettner | W68: 8790 | X68: 25000 | Y68: =IF(OR(W68="",W68=0,X68=""),"",X68/W68) -> 2.8441411 | Z68: 4 | AA68: https://youtu.be/FSs0OZCzPlA | AB68: Planned | AE68: =IF(AB68<>"Published",COUNTIF($AB$2:AB68,"<>Published"),"") -> 67
A69: 68 | B69: =ROUNDUP(A69/3,0) -> 23 | C69: Phase 3: econometrics & game theory heavy; IB anchor; remaining topics | D69: EC-11 | E69: Econometrics | F69: Huntington-Klein, The Effect (free online) Ch.19 Instrumental variables | G69: Instrumental variables: finding a natural experiment inside your data | H69: Explainer | I69: 12-15 min | J69: EC-09 | K69: University | L69: High | M69: Stale (median outlier age 8y+) | N69: 19 | O69: 7 | P69: 5 | Q69: 1 | R69: 17.88 | S69: 1.63 | T69: 11 | U69: An intuitive introduction to Instrumental Variables | V69: Doug McKee | W69: 5480 | X69: 98000 | Y69: =IF(OR(W69="",W69=0,X69=""),"",X69/W69) -> 17.883212 | Z69: 11 | AA69: https://youtu.be/FQ3d2syNfYI | AB69: Planned | AE69: =IF(AB69<>"Published",COUNTIF($AB$2:AB69,"<>Published"),"") -> 68
A70: 69 | B70: =ROUNDUP(A70/3,0) -> 23 | C70: Phase 3: econometrics & game theory heavy; IB anchor; remaining topics | D70: GT-11 | E70: Game Theory | F70: Bonanno, Game Theory (open access, UC Davis) Ch.3 Bargaining | G70: Bargaining: the ultimatum game and the Nash bargaining solution | H70: Explainer | I70: 8-10 min | J70: GT-04 | K70: University | L70: Low | M70: - | N70: 4 | O70: 2 | P70: 0 | Q70: 0 | R70: 0.24 | S70: 0.02 | U70: Bargaining game Backward Induction equilibrium Part 1 | V70: ecopoint | W70: 29500 | X70: 7200 | Y70: =IF(OR(W70="",W70=0,X70=""),"",X70/W70) -> 0.2440678 | Z70: 13 | AA70: https://youtu.be/o49kET4Jb0c | AB70: Planned | AE70: =IF(AB70<>"Published",COUNTIF($AB$2:AB70,"<>Published"),"") -> 69
A71: 70 | B71: =ROUNDUP(A71/3,0) -> 24 | C71: Phase 3: econometrics & game theory heavy; IB anchor; remaining topics | D71: MI-21 | E71: Intermediate Microeconomics | F71: McAfee & Lewis, Introduction to Economic Analysis (CC BY-NC-SA) §7 Externalities | G71: Externalities: the social cost curve and the Pigouvian tax | H71: Explainer | I71: 8-10 min | J71: MI-05 | K71: IB/A-level/AP | L71: High | M71: Stale (median outlier age 8y+) | N71: 93 | O71: 26 | P71: 14 | Q71: 1 | R71: 9.02 | S71: 4.96 | T71: 8 | U71: Externalities | V71: Economics Online | W71: 5990 | X71: 54000 | Y71: =IF(OR(W71="",W71=0,X71=""),"",X71/W71) -> 9.015025 | Z71: 7 | AA71: https://youtu.be/4V1ncb2nCG0 | AB71: Planned | AE71: =IF(AB71<>"Published",COUNTIF($AB$2:AB71,"<>Published"),"") -> 70
A72: 71 | B72: =ROUNDUP(A72/3,0) -> 24 | C72: Phase 3: econometrics & game theory heavy; IB anchor; remaining topics | D72: MA-22 | E72: Intermediate Macroeconomics | F72: Garín, Lester & Sims, Intermediate Macroeconomics (free PDF) Ch.23 Expectations | G72: Rational expectations and the Lucas critique | H72: Explainer | I72: 10-12 min | J72: MA-15 | K72: University | L72: Low | M72: - | N72: 3 | O72: 3 | P72: 0 | Q72: 0 | R72: 0.31 | S72: 0.08 | U72: Rational Expectations Theory by Vidhi Kalra | V72: 5 Minute Economics | W72: 99200 | X72: 31000 | Y72: =IF(OR(W72="",W72=0,X72=""),"",X72/W72) -> 0.3125 | Z72: 4 | AA72: https://youtu.be/mVdrKbwal9k | AB72: Planned | AE72: =IF(AB72<>"Published",COUNTIF($AB$2:AB72,"<>Published"),"") -> 71
A73: 72 | B73: =ROUNDUP(A73/3,0) -> 24 | C73: Phase 3: econometrics & game theory heavy; IB anchor; remaining topics | D73: EC-12 | E73: Econometrics | F73: Huntington-Klein, The Effect (free online) Ch.20 Regression discontinuity | G73: Regression discontinuity: when a cutoff is your experiment | H73: Explainer | I73: 10-12 min | J73: EC-09 | K73: University | L73: High | M73: Stale (median outlier age 8y+) | N73: 4 | O73: 4 | P73: 1 | Q73: 1 | R73: 23.36 | S73: 2.12 | T73: 11 | U73: An intuitive introduction to Regression Discontinuity | V73: Doug McKee | W73: 5480 | X73: 128000 | Y73: =IF(OR(W73="",W73=0,X73=""),"",X73/W73) -> 23.357664 | Z73: 11 | AA73: https://youtu.be/tWRsYWSP3fM | AB73: Planned | AE73: =IF(AB73<>"Published",COUNTIF($AB$2:AB73,"<>Published"),"") -> 72
A74: 73 | B74: =ROUNDUP(A74/3,0) -> 25 | C74: Phase 3: econometrics & game theory heavy; IB anchor; remaining topics | D74: GT-12 | E74: Game Theory | F74: Bonanno, Game Theory (open access, UC Davis) Applications | G74: Cournot as a game: oligopoly through the Nash lens | H74: Explainer | I74: 8-10 min | J74: GT-02, MI-17 | K74: University | L74: Medium | M74: Ageing (4-8y) | N74: 3 | O74: 3 | P74: 1 | Q74: 0 | R74: 2.03 | S74: 0.94 | T74: 4 | U74: Micro 4.5 - Oligopoly and Game Theory: What you need to know for the exam! | V74: ReviewEcon | W74: 47700 | X74: 97000 | Y74: =IF(OR(W74="",W74=0,X74=""),"",X74/W74) -> 2.033543 | Z74: 4 | AA74: https://youtu.be/ZbFkPoklBPw | AB74: Planned | AE74: =IF(AB74<>"Published",COUNTIF($AB$2:AB74,"<>Published"),"") -> 73
A75: 74 | B75: =ROUNDUP(A75/3,0) -> 25 | C75: Phase 3: econometrics & game theory heavy; IB anchor; remaining topics | D75: MI-22 | E75: Intermediate Microeconomics | F75: McAfee & Lewis, Introduction to Economic Analysis (CC BY-NC-SA) §7.3 Coase | G75: The Coase theorem: when property rights fix externalities | H75: Explainer | I75: 8-10 min | J75: MI-21 | K75: University | L75: Medium | M75: Stale (median outlier age 8y+) | N75: 10 | O75: 8 | P75: 1 | Q75: 0 | R75: 5.71 | S75: 0.81 | T75: 8 | U75: The Coase Theorem | V75: Principles of Microeconomics | W75: 11200 | X75: 64000 | Y75: =IF(OR(W75="",W75=0,X75=""),"",X75/W75) -> 5.7142857 | Z75: 8 | AA75: https://youtu.be/EsYDVW2na7c | AB75: Planned | AE75: =IF(AB75<>"Published",COUNTIF($AB$2:AB75,"<>Published"),"") -> 74
A76: 75 | B76: =ROUNDUP(A76/3,0) -> 25 | C76: Phase 3: econometrics & game theory heavy; IB anchor; remaining topics | D76: MA-23 | E76: Intermediate Macroeconomics | F76: Garín, Lester & Sims, Intermediate Macroeconomics (free PDF) Ch.27 Zero lower bound | G76: Quantitative easing and the zero lower bound: what the Fed actually did | H76: Explainer | I76: 10-12 min | J76: MA-16 | K76: University | L76: Medium | M76: Stale (median outlier age 8y+) | N76: 14 | O76: 12 | P76: 1 | Q76: 0 | R76: 1.45 | S76: 0.16 | T76: 15 | U76: fiscal policy and deficit problems; quantitative easing | V76: pajholden | W76: 47500 | X76: 69000 | Y76: =IF(OR(W76="",W76=0,X76=""),"",X76/W76) -> 1.4526316 | Z76: 15 | AA76: https://youtu.be/wPnvZ8tKA74 | AB76: Planned | AE76: =IF(AB76<>"Published",COUNTIF($AB$2:AB76,"<>Published"),"") -> 75
A77: 76 | B77: =ROUNDUP(A77/3,0) -> 26 | C77: Phase 3: econometrics & game theory heavy; IB anchor; remaining topics | D77: EC-13 | E77: Econometrics | F77: Hanck et al., Introduction to Econometrics with R (CC BY-NC-SA) Ch.10 Panel data | G77: Panel data and fixed effects: controlling for what you can't see | H77: Explainer | I77: 12-15 min | J77: EC-04 | K77: University | L77: Medium | M77: Stale (median outlier age 8y+) | N77: 16 | O77: 5 | P77: 6 | Q77: 0 | R77: 7.63 | S77: 0.54 | T77: 13 | U77: Panel Data Models in Stata | V77: econometricsacademy | W77: 76100 | X77: 505000 | Y77: =IF(OR(W77="",W77=0,X77=""),"",X77/W77) -> 6.6360053 | Z77: 13 | AA77: https://youtu.be/TBV9QFMJqoE | AB77: Planned | AE77: =IF(AB77<>"Published",COUNTIF($AB$2:AB77,"<>Published"),"") -> 76
A78: 77 | B78: =ROUNDUP(A78/3,0) -> 26 | C78: Phase 3: econometrics & game theory heavy; IB anchor; remaining topics | D78: GT-13 | E78: Game Theory | F78: Bonanno, Game Theory (open access, UC Davis) Applications | G78: Evolutionary game theory: hawks, doves and stable strategies | H78: Explainer | I78: 10-12 min | J78: GT-06 | K78: University | L78: Low | M78: - | N78: 3 | O78: 2 | P78: 0 | Q78: 0 | R78: 0.7 | S78: 0.23 | U78: Game of Chicken / Hawk-Dove in Game Theory | V78: Ashley Hodgson | W78: 55600 | X78: 39000 | Y78: =IF(OR(W78="",W78=0,X78=""),"",X78/W78) -> 0.70143885 | Z78: 3 | AA78: https://youtu.be/Q1DVAFRuAtI | AB78: Planned | AE78: =IF(AB78<>"Published",COUNTIF($AB$2:AB78,"<>Published"),"") -> 77
A79: 78 | B79: =ROUNDUP(A79/3,0) -> 26 | C79: Phase 3: econometrics & game theory heavy; IB anchor; remaining topics | D79: MI-23 | E79: Intermediate Microeconomics | F79: McAfee & Lewis, Introduction to Economic Analysis (CC BY-NC-SA) §7.4 Public goods | G79: Public goods and the free-rider problem | H79: Explainer | I79: 6-8 min | J79: MI-21 | K79: IB/A-level | L79: Medium | M79: Stale (median outlier age 8y+) | N79: 40 | O79: 24 | P79: 1 | Q79: 0 | R79: 1.6 | S79: 1.13 | T79: 8 | U79: 🐄 The Tragedy of the Commons | How to Avoid It? | V79: EconClips | W79: 113000 | X79: 148000 | Y79: =IF(OR(W79="",W79=0,X79=""),"",X79/W79) -> 1.3097345 | Z79: 8 | AA79: https://youtu.be/tLnA0AO2lXA | AB79: Planned | AE79: =IF(AB79<>"Published",COUNTIF($AB$2:AB79,"<>Published"),"") -> 78
A80: 79 | B80: =ROUNDUP(A80/3,0) -> 27 | C80: Phase 3: econometrics & game theory heavy; IB anchor; remaining topics | D80: MA-24 | E80: Intermediate Macroeconomics | F80: Garín, Lester & Sims, Intermediate Macroeconomics (free PDF) Ch.5 Convergence | G80: Why poor countries don't always catch up: convergence and the Solow puzzle | H80: Explainer | I80: 10-12 min | J80: MA-05 | K80: University | L80: High | M80: Fresh (<4y) | N80: 100 | O80: 39 | P80: 5 | Q80: 2 | R80: 7.8 | S80: 2.6 | T80: 2 | U80: Why Africa is so Poor (Hint: It isn’t Colonialism) | V80: The Why Minutes | W80: 141000 | X80: 1100000 | Y80: =IF(OR(W80="",W80=0,X80=""),"",X80/W80) -> 7.8014184 | Z80: 3 | AA80: https://youtu.be/to0I0kS8FcU | AB80: Planned | AE80: =IF(AB80<>"Published",COUNTIF($AB$2:AB80,"<>Published"),"") -> 79
A81: 80 | B81: =ROUNDUP(A81/3,0) -> 27 | C81: Phase 3: econometrics & game theory heavy; IB anchor; remaining topics | D81: GT-14 | E81: Game Theory | F81: Bonanno, Game Theory (open access, UC Davis) (whole) | G81: ALL of Game Theory in 15 minutes | H81: Anchor (ALL of…) | I81: 15 min | J81: GT-01…GT-13 | K81: University | L81: Low | M81: - | N81: 1 | O81: 1 | P81: 0 | Q81: 0 | R81: 0.02 | S81: 0 | U81: What Is Game Theory? Explained In 4 Minutes | V81: Ryan O'Connell, CFA, FRM | W81: 80400 | X81: 1400 | Y81: =IF(OR(W81="",W81=0,X81=""),"",X81/W81) -> 0.017412935 | Z81: 0.25 | AA81: https://youtu.be/HiJjJL-39e0 | AB81: Planned | AE81: =IF(AB81<>"Published",COUNTIF($AB$2:AB81,"<>Published"),"") -> 80
A82: 81 | B82: =ROUNDUP(A82/3,0) -> 27 | C82: Phase 3: econometrics & game theory heavy; IB anchor; remaining topics | D82: EC-14 | E82: Econometrics | F82: Huntington-Klein, The Effect (free online) Ch.21 Event studies | G82: Event studies and staggered treatment: the modern DiD problem | H82: Explainer | I82: 10-12 min | J82: EC-10, EC-13 | K82: University | L82: Low | M82: - | N82: 3 | O82: 2 | P82: 0 | Q82: 0 | R82: 0.15 | S82: 0.23 | U82: Event Study in Stata (Step-by-Step with Simulated Data) | V82: In Case of Econ Struggles | W82: 5070 | X82: 779 | Y82: =IF(OR(W82="",W82=0,X82=""),"",X82/W82) -> 0.15364892 | Z82: 0.67 | AA82: https://youtu.be/WOtVrPWvhcM | AB82: Planned | AE82: =IF(AB82<>"Published",COUNTIF($AB$2:AB82,"<>Published"),"") -> 81
A83: 82 | B83: =ROUNDUP(A83/3,0) -> 28 | C83: Phase 3: econometrics & game theory heavy; IB anchor; remaining topics | D83: MI-24 | E83: Intermediate Microeconomics | F83: McAfee & Lewis, Introduction to Economic Analysis (CC BY-NC-SA) §18 Information: adverse selection | G83: Adverse selection and moral hazard: why used cars and insurance are hard | H83: Explainer | I83: 8-10 min | J83: MI-01 | K83: University | L83: Medium | M83: Ageing (4-8y) | N83: 19 | O83: 12 | P83: 1 | Q83: 1 | R83: 8.83 | S83: 1.47 | T83: 6 | U83: Asymmetric Information, Adverse Selection & Moral Hazard | Economics Explained | V83: INOMICS | W83: 15400 | X83: 136000 | Y83: =IF(OR(W83="",W83=0,X83=""),"",X83/W83) -> 8.8311688 | Z83: 6 | AA83: https://youtu.be/39QhA4qCOec | AB83: Planned | AE83: =IF(AB83<>"Published",COUNTIF($AB$2:AB83,"<>Published"),"") -> 82
A84: 83 | B84: =ROUNDUP(A84/3,0) -> 28 | C84: Phase 3: econometrics & game theory heavy; IB anchor; remaining topics | D84: EC-15 | E84: Econometrics | F84: Hanck et al., Introduction to Econometrics with R (CC BY-NC-SA) Ch.11 Binary outcomes | G84: Probit and logit: regression when y is yes/no | H84: Explainer | I84: 10-12 min | J84: EC-04 | K84: University | L84: Medium | M84: Stale (median outlier age 8y+) | N84: 25 | O84: 4 | P84: 7 | Q84: 0 | R84: 3.94 | S84: 0.3 | T84: 13 | U84: Probit and Logit Models | V84: econometricsacademy | W84: 76100 | X84: 300000 | Y84: =IF(OR(W84="",W84=0,X84=""),"",X84/W84) -> 3.9421813 | Z84: 13 | AA84: https://youtu.be/1cFYlMjEz-c | AB84: Planned | AE84: =IF(AB84<>"Published",COUNTIF($AB$2:AB84,"<>Published"),"") -> 83
A85: 84 | B85: =ROUNDUP(A85/3,0) -> 28 | C85: Phase 3: econometrics & game theory heavy; IB anchor; remaining topics | D85: MI-25 | E85: Intermediate Microeconomics | F85: McAfee & Lewis, Introduction to Economic Analysis (CC BY-NC-SA) §13 General equilibrium | G85: The Edgeworth box: general equilibrium in one picture | H85: Explainer | I85: 10-12 min | J85: MI-06 | K85: University | L85: Medium | M85: Fresh (<4y) | N85: 19 | O85: 7 | P85: 4 | Q85: 1 | R85: 3.16 | S85: 1.14 | T85: 3.5 | U85: Edgeworth Box | V85: Ashley Hodgson | W85: 55600 | X85: 175000 | Y85: =IF(OR(W85="",W85=0,X85=""),"",X85/W85) -> 3.147482 | Z85: 11 | AA85: https://youtu.be/Bjg-KPQhWyM | AB85: Planned | AE85: =IF(AB85<>"Published",COUNTIF($AB$2:AB85,"<>Published"),"") -> 84
A86: 85 | B86: =ROUNDUP(A86/3,0) -> 29 | C86: Phase 3: econometrics & game theory heavy; IB anchor; remaining topics | D86: EC-16 | E86: Econometrics | F86: Hanck et al., Introduction to Econometrics with R (CC BY-NC-SA) Ch.14 Time series | G86: Time series basics: stationarity, autocorrelation and spurious regression | H86: Explainer | I86: 12-15 min | J86: EC-01 | K86: University | L86: Medium | M86: Stale (median outlier age 8y+) | N86: 16 | O86: 6 | P86: 7 | Q86: 0 | R86: 4.65 | S86: 0.71 | T86: 12 | U86: Time Series ARIMA Models | V86: econometricsacademy | W86: 76100 | X86: 354000 | Y86: =IF(OR(W86="",W86=0,X86=""),"",X86/W86) -> 4.651774 | Z86: 12 | AA86: https://youtu.be/Y2khrpVo6qI | AB86: Planned | AE86: =IF(AB86<>"Published",COUNTIF($AB$2:AB86,"<>Published"),"") -> 85
A87: 86 | B87: =ROUNDUP(A87/3,0) -> 29 | C87: Phase 3: econometrics & game theory heavy; IB anchor; remaining topics | D87: MI-26 | E87: Intermediate Microeconomics | F87: McAfee & Lewis, Introduction to Economic Analysis (CC BY-NC-SA) §11 Factor markets | G87: Labour markets and the minimum wage, with and without monopsony | H87: Explainer | I87: 10-12 min | J87: MI-12 | K87: IB/A-level/AP | L87: Medium | M87: Ageing (4-8y) | N87: 80 | O87: 34 | P87: 9 | Q87: 1 | R87: 6.6 | S87: 1.1 | T87: 6 | U87: Microeconomics Unit 5 COMPLETE Summary - Factor Markets | V87: ReviewEcon | W87: 47700 | X87: 315000 | Y87: =IF(OR(W87="",W87=0,X87=""),"",X87/W87) -> 6.6037736 | Z87: 6 | AA87: https://youtu.be/Cb5rAZZSJfg | AB87: Planned | AE87: =IF(AB87<>"Published",COUNTIF($AB$2:AB87,"<>Published"),"") -> 86
A88: 87 | B88: =ROUNDUP(A88/3,0) -> 29 | C88: Phase 3: econometrics & game theory heavy; IB anchor; remaining topics | D88: EC-17 | E88: Econometrics | F88: Hanck et al., Introduction to Econometrics with R (CC BY-NC-SA) Ch.14.4 ARIMA | G88: ARIMA models, explained without the alphabet soup | H88: Explainer | I88: 12-15 min | J88: EC-16 | K88: University | L88: Medium | M88: Stale (median outlier age 8y+) | N88: 7 | O88: 2 | P88: 4 | Q88: 0 | R88: 4.65 | S88: 0.39 | T88: 12 | U88: Time Series ARIMA Models | V88: econometricsacademy | W88: 76100 | X88: 354000 | Y88: =IF(OR(W88="",W88=0,X88=""),"",X88/W88) -> 4.651774 | Z88: 12 | AA88: https://youtu.be/Y2khrpVo6qI | AB88: Planned | AE88: =IF(AB88<>"Published",COUNTIF($AB$2:AB88,"<>Published"),"") -> 87
A89: 88 | B89: =ROUNDUP(A89/3,0) -> 30 | C89: Phase 3: econometrics & game theory heavy; IB anchor; remaining topics | D89: MI-27 | E89: Intermediate Microeconomics | F89: McAfee & Lewis, Introduction to Economic Analysis (CC BY-NC-SA) §4 Trade: comparative advantage | G89: Comparative advantage: how to work out who should make what | H89: Worked problem ("how to solve") | I89: 8-10 min | J89: MI-03 | K89: IB/A-level/AP | L89: High | M89: Ageing (4-8y) | N89: 52 | O89: 23 | P89: 6 | Q89: 1 | R89: 10.46 | S89: 1.81 | T89: 6.5 | U89: absolute and comparative advantage | V89: pajholden | W89: 47500 | X89: 497000 | Y89: =IF(OR(W89="",W89=0,X89=""),"",X89/W89) -> 10.463158 | Z89: 18 | AA89: https://youtu.be/Pd_qs8ueIWw | AB89: Planned | AE89: =IF(AB89<>"Published",COUNTIF($AB$2:AB89,"<>Published"),"") -> 88
A90: 89 | B90: =ROUNDUP(A90/3,0) -> 30 | C90: Phase 3: econometrics & game theory heavy; IB anchor; remaining topics | D90: EC-18 | E90: Econometrics | F90: Hanck et al., Introduction to Econometrics with R (CC BY-NC-SA) Ch.16 Cointegration | G90: Cointegration and error correction: when two random walks move together | H90: Explainer | I90: 10-12 min | J90: EC-16 | K90: University | L90: No comparable video | M90: - | N90: 0 | O90: 0 | P90: 0 | Q90: 0 | R90: 0 | S90: 0 | Y90: =IF(OR(W90="",W90=0,X90=""),"",X90/W90) | AB90: Planned | AE90: =IF(AB90<>"Published",COUNTIF($AB$2:AB90,"<>Published"),"") -> 89
A91: 90 | B91: =ROUNDUP(A91/3,0) -> 30 | C91: Phase 3: econometrics & game theory heavy; IB anchor; remaining topics | D91: EC-19 | E91: Econometrics | F91: Cunningham, Causal Inference: The Mixtape (free online) Ch.5 Matching | G91: Propensity score matching: comparing like with like | H91: Explainer | I91: 10-12 min | J91: EC-09 | K91: University | L91: High | M91: Stale (median outlier age 8y+) | N91: 11 | O91: 7 | P91: 4 | Q91: 1 | R91: 42.34 | S91: 3.85 | T91: 13 | U91: An intuitive introduction to Propensity Score Matching | V91: Doug McKee | W91: 5480 | X91: 232000 | Y91: =IF(OR(W91="",W91=0,X91=""),"",X91/W91) -> 42.335766 | Z91: 11 | AA91: https://youtu.be/ACVyPp1Fy6Y | AB91: Planned | AE91: =IF(AB91<>"Published",COUNTIF($AB$2:AB91,"<>Published"),"") -> 90
A92: 91 | B92: =ROUNDUP(A92/3,0) -> 31 | C92: Phase 4: compressions & format experiments | D92: EC-20 | E92: Econometrics | F92: Huntington-Klein, The Effect (free online) Ch.13 Measurement error | G92: Measurement error and attenuation bias | H92: Explainer | I92: 8-10 min | J92: EC-04 | K92: University | L92: No comparable video | M92: - | N92: 0 | O92: 0 | P92: 0 | Q92: 0 | R92: 0 | S92: 0 | Y92: =IF(OR(W92="",W92=0,X92=""),"",X92/W92) | AB92: Planned | AE92: =IF(AB92<>"Published",COUNTIF($AB$2:AB92,"<>Published"),"") -> 91
A93: 92 | B93: =ROUNDUP(A93/3,0) -> 31 | C93: Phase 4: compressions & format experiments | D93: EC-21 | E93: Econometrics | F93: Huntington-Klein, The Effect (free online) Ch.9 Selection | G93: Sample selection bias (and the Heckman fix) | H93: Explainer | I93: 10-12 min | J93: EC-08 | K93: University | L93: Low | M93: - | N93: 3 | O93: 3 | P93: 0 | Q93: 0 | R93: 0.79 | S93: 0.26 | U93: The 6 Minute Review Guide on Selection Bias, ATT, and ATE | V93: In Case of Econ Struggles | W93: 5070 | X93: 4000 | Y93: =IF(OR(W93="",W93=0,X93=""),"",X93/W93) -> 0.78895464 | Z93: 3 | AA93: https://youtu.be/jVkQPnARPQ0 | AB93: Planned | AE93: =IF(AB93<>"Published",COUNTIF($AB$2:AB93,"<>Published"),"") -> 92
A94: 93 | B94: =ROUNDUP(A94/3,0) -> 31 | C94: Phase 4: compressions & format experiments | D94: EC-22 | E94: Econometrics | F94: Hanck et al., Introduction to Econometrics with R (CC BY-NC-SA) Appendix: software | G94: Your first regression in R and Python, side by side | H94: Worked problem ("how to solve") | I94: 10-12 min | J94: EC-01 | K94: University | L94: Medium | M94: Stale (median outlier age 8y+) | N94: 89 | O94: 5 | P94: 13 | Q94: 0 | R94: 10.43 | S94: 0.97 | T94: 13 | U94: Stata Tutorial: Introduction to Stata | V94: econometricsacademy | W94: 76100 | X94: 794000 | Y94: =IF(OR(W94="",W94=0,X94=""),"",X94/W94) -> 10.43364 | Z94: 13 | AA94: https://youtu.be/YMt5K68ZvjQ | AB94: Planned | AE94: =IF(AB94<>"Published",COUNTIF($AB$2:AB94,"<>Published"),"") -> 93
A95: 94 | B95: =ROUNDUP(A95/3,0) -> 32 | C95: Phase 4: compressions & format experiments | D95: EC-23 | E95: Econometrics | F95: Huntington-Klein, The Effect (free online) Ch.22 Synthetic control | G95: Synthetic control: building a counterfactual country | H95: Explainer | I95: 10-12 min | J95: EC-10 | K95: University | L95: Low | M95: - | N95: 1 | O95: 1 | P95: 0 | Q95: 0 | R95: 0.03 | S95: 0 | U95: Synthetic Control and the Impact of Hugo Chavez with Kevin B. Grier | V95: The Economics Detective | W95: 34000 | X95: 1000 | Y95: =IF(OR(W95="",W95=0,X95=""),"",X95/W95) -> 0.029411765 | Z95: 8 | AA95: https://youtu.be/puZvQPudk6E | AB95: Planned | AE95: =IF(AB95<>"Published",COUNTIF($AB$2:AB95,"<>Published"),"") -> 94
A96: 95 | B96: =ROUNDUP(A96/3,0) -> 32 | C96: Phase 4: compressions & format experiments | D96: EC-24 | E96: Econometrics | F96: Hanck et al., Introduction to Econometrics with R (CC BY-NC-SA) Ch.4 Regression anatomy | G96: Frisch-Waugh-Lovell: what a coefficient really is in multiple regression | H96: Explainer | I96: 8-10 min | J96: EC-04 | K96: University | L96: No comparable video | M96: - | N96: 0 | O96: 0 | P96: 0 | Q96: 0 | R96: 0 | S96: 0 | Y96: =IF(OR(W96="",W96=0,X96=""),"",X96/W96) | AB96: Planned | AE96: =IF(AB96<>"Published",COUNTIF($AB$2:AB96,"<>Published"),"") -> 95
A97: 96 | B97: =ROUNDUP(A97/3,0) -> 32 | C97: Phase 4: compressions & format experiments | D97: EC-26 | E97: Econometrics | F97: Hanck et al., Introduction to Econometrics with R (CC BY-NC-SA) Ch.7 Specification | G97: Functional form and specification errors: when the model is wrong, not the data | H97: Explainer | I97: 8-10 min | J97: EC-04 | K97: University | L97: Low | M97: - | N97: 7 | O97: 5 | P97: 0 | Q97: 0 | R97: 0.4 | S97: 0.05 | U97: R Spatial Regression 2: All Spatial Models and Specification Tests | V97: BurkeyAcademy | W97: 37100 | X97: 15000 | Y97: =IF(OR(W97="",W97=0,X97=""),"",X97/W97) -> 0.40431267 | Z97: 8 | AA97: https://youtu.be/MbQ4s8lwqGI | AB97: Planned | AE97: =IF(AB97<>"Published",COUNTIF($AB$2:AB97,"<>Published"),"") -> 96
A98: 97 | B98: =ROUNDUP(A98/3,0) -> 33 | C98: Phase 4: compressions & format experiments | D98: XC-02 | E98: Cross-course | F98: 5-levels format | G98: Supply and demand in 5 levels: high school to PhD | H98: Explainer | I98: 10-12 min | J98: MI-01 | K98: IB/A-level/University | L98: Low | M98: - | N98: 1 | O98: 1 | P98: 0 | Q98: 0 | R98: 0.23 | S98: 0.06 | U98: Prospect Theory Explained at 5 Levels of Difficulty | V98: Pete Judo | W98: 115000 | X98: 27000 | Y98: =IF(OR(W98="",W98=0,X98=""),"",X98/W98) -> 0.23478261 | Z98: 4 | AA98: https://youtu.be/RfS11SRQC20 | AB98: Planned | AE98: =IF(AB98<>"Published",COUNTIF($AB$2:AB98,"<>Published"),"") -> 97
A99: 98 | B99: =ROUNDUP(A99/3,0) -> 33 | C99: Phase 4: compressions & format experiments | D99: XC-03 | E99: Cross-course | F99: History-of-an-idea format | G99: How Solow discovered that capital isn't what makes countries rich | H99: Explainer | I99: 15-20 min | J99: MA-04 | K99: University | L99: Low | M99: - | N99: 1 | O99: 1 | P99: 0 | Q99: 0 | R99: 0.05 | S99: 0.01 | U99: How We Discovered North Korea Is Poor | V99: Market Power | W99: 68800 | X99: 3600 | Y99: =IF(OR(W99="",W99=0,X99=""),"",X99/W99) -> 0.052325581 | Z99: 5 | AA99: https://youtu.be/WF4jfq-ny_Q | AB99: Planned | AE99: =IF(AB99<>"Published",COUNTIF($AB$2:AB99,"<>Published"),"") -> 98
A100: 99 | B100: =ROUNDUP(A100/3,0) -> 33 | C100: Phase 4: compressions & format experiments | D100: EC-25 | E100: Econometrics | F100: Cunningham, Causal Inference: The Mixtape (free online) (whole) | G100: ALL of Econometrics in 20 minutes | H100: Anchor (ALL of…) | I100: 20 min | J100: EC-01…EC-24 | K100: University | L100: High | M100: Stale (median outlier age 8y+) | N100: 6 | O100: 5 | P100: 3 | Q100: 1 | R100: 31.96 | S100: 2.46 | T100: 13 | U100: Econometrics // Lecture 1: Introduction | V100: KeynesAcademy | W100: 28100 | X100: 898000 | Y100: =IF(OR(W100="",W100=0,X100=""),"",X100/W100) -> 31.957295 | Z100: 13 | AA100: https://youtu.be/vEP4RIOKuE4 | AB100: Planned | AE100: =IF(AB100<>"Published",COUNTIF($AB$2:AB100,"<>Published"),"") -> 99
A101: 100 | B101: =ROUNDUP(A101/3,0) -> 34 | C101: Phase 4: compressions & format experiments | D101: XC-01 | E101: Cross-course | F101: Compression format | G101: The Entire Economics Degree, explained properly, in 30 minutes | H101: Anchor (ALL of…) | I101: 30 min | J101: MI-28, MA-26, GT-14, EC-25 | K101: University | L101: High | M101: Fresh (<4y) | N101: 1 | O101: 1 | P101: 1 | Q101: 1 | R101: 21.38 | S101: 21.38 | T101: 1 | U101: The Entire Economics Degree in 20 Minutes | V101: 20 Minute University | W101: 145000 | X101: 3100000 | Y101: =IF(OR(W101="",W101=0,X101=""),"",X101/W101) -> 21.37931 | Z101: 1 | AA101: https://youtu.be/NngM_qdDMm8 | AB101: Planned | AE101: =IF(AB101<>"Published",COUNTIF($AB$2:AB101,"<>Published"),"") -> 100

Sheet Schedule
A1: Week | B1: Phase | C1: Video 1 | D1: Video 2 | E1: Video 3
A2: 1 | B2: Phase 1: intermediate micro + macro, textbook order | C2: MI-01 Supply and demand, properly: what shifts a curve and what moves along it | D2: MA-01 GDP, properly: three ways to measure one number | E2: MI-02 How to solve elasticity problems (point, arc, revenue test)
A3: 2 | B3: Phase 1: intermediate micro + macro, textbook order | C3: MA-02 Inflation, the CPI and the GDP deflator (and why they disagree) | D3: MI-03 How to calculate opportunity cost (and why the PPF is curved) | E3: MA-03 The aggregate production function and diminishing returns to capital
A4: 3 | B4: Phase 1: intermediate micro + macro, textbook order | C4: MI-04 Consumer and producer surplus: how to calculate them from a graph | D4: MA-04 The Solow growth model, part 1: the diagram and the steady state | E4: MI-05 Price ceilings, floors and taxes: who really pays?
A5: 4 | B5: Phase 1: intermediate micro + macro, textbook order | C5: MA-05 Solow part 2: population, technology and the golden rule | D5: MI-06 Indifference curves and the budget constraint, visualised | E5: MA-06 Growth accounting: how much of growth is capital, labour and ideas?
A6: 5 | B6: Phase 1: intermediate micro + macro, textbook order | C6: MI-07 Income vs substitution effects (the Slutsky decomposition, step by step) | D6: MA-07 Consumption smoothing: the two-period model and permanent income | E6: MI-29 The labour-leisure choice: why higher wages don't always mean more work
A7: 6 | B7: Phase 1: intermediate micro + macro, textbook order | C7: MA-26 Investment: Tobin's q and the user cost of capital | D7: MI-30 Saving and borrowing: the intertemporal budget constraint | E7: MA-08 Unemployment: natural rate, cyclical and the labour market diagram
A8: 7 | B8: Phase 1: intermediate micro + macro, textbook order | C8: MI-08 Marginal utility and why demand slopes down | D8: MA-09 How banks create money (the balance-sheet version) | E8: MI-09 How to calculate marginal, average and total cost (and draw the curves)
A9: 8 | B9: Phase 1: intermediate micro + macro, textbook order | C9: MA-10 The IS curve, derived: goods-market equilibrium and the multiplier | D9: MI-10 Economies of scale and the long-run average cost curve | E9: MA-11 The LM curve, derived: money-market equilibrium
A10: 9 | B10: Phase 2: micro / macro / game theory / econometrics rotation; micro & macro anchors | C10: MI-11 Cobb-Douglas: the production function that runs economics | D10: MA-12 The IS-LM model: fiscal and monetary policy in one diagram | E10: GT-01 Game theory from zero: payoff matrices and dominant strategies
A11: 10 | B11: Phase 2: micro / macro / game theory / econometrics rotation; micro & macro anchors | C11: EC-01 Simple linear regression: what OLS actually minimises (and why) | D11: MI-28 ALL of Intermediate Microeconomics in 20 minutes | E11: MI-12 Perfect competition: profit maximisation and the shutdown rule
A12: 11 | B12: Phase 2: micro / macro / game theory / econometrics rotation; micro & macro anchors | C12: MA-13 The AD-AS model: demand and supply shocks, short run to long run | D12: GT-02 How to find a Nash equilibrium in a 2×2 game | E12: EC-02 R² explained: what it measures and the three ways people misuse it
A13: 12 | B13: Phase 2: micro / macro / game theory / econometrics rotation; micro & macro anchors | C13: MI-13 From short run to long run in perfect competition (why profits vanish) | D13: MA-14 The Phillips curve: why it worked, broke, and came back | E13: GT-03 The prisoner's dilemma: why rational players lose
... A34: 33 | B34: Phase 4: compressions & format experiments | C34: XC-02 Supply and demand in 5 levels: high school to PhD | D34: XC-03 How Solow discovered that capital isn't what makes countries rich | E34: EC-25 ALL of Econometrics in 20 minutes
A35: 34 | B35: Phase 4: compressions & format experiments | C35: XC-01 The Entire Economics Degree, explained properly, in 30 minutes

Sheet By Course
A1: Course | B1: Code | C1: Working title | D1: Source section | E1: Format | F1: Length | G1: Prerequisites | H1: Exam tag | I1: Demand signal | J1: Supply age | K1: Production order
A2: Intermediate Microeconomics | B2: MI-01 | C2: Supply and demand, properly: what shifts a curve and what moves along it | D2: McAfee & Lewis, Introduction to Economic Analysis (CC BY-NC-SA) §2 Supply and Demand | E2: Explainer | F2: 8-10 min | G2: None | H2: IB/A-level/AP | I2: High | J2: Stale (median outlier age 8y+) | K2: 1
A3: Intermediate Microeconomics | B3: MI-02 | C3: How to solve elasticity problems (point, arc, revenue test) | D3: McAfee & Lewis, Introduction to Economic Analysis (CC BY-NC-SA) §2.3 Elasticity | E3: Worked problem ("how to solve") | F3: 8-10 min | G3: MI-01 | H3: IB/A-level/AP | I3: High | J3: Stale (median outlier age 8y+) | K3: 3
A4: Intermediate Microeconomics | B4: MI-03 | C4: How to calculate opportunity cost (and why the PPF is curved) | D4: McAfee & Lewis, Introduction to Economic Analysis (CC BY-NC-SA) §2.1 Opportunity cost / PPF | E4: Worked problem ("how to solve") | F4: 6-8 min | G4: None | H4: IB/A-level/AP | I4: High | J4: Stale (median outlier age 8y+) | K4: 5
A5: Intermediate Microeconomics | B5: MI-04 | C5: Consumer and producer surplus: how to calculate them from a graph | D5: McAfee & Lewis, Introduction to Economic Analysis (CC BY-NC-SA) §2.5 Surplus | E5: Worked problem ("how to solve") | F5: 6-8 min | G5: MI-01 | H5: IB/A-level/AP | I5: High | J5: Stale (median outlier age 8y+) | K5: 7
A6: Intermediate Microeconomics | B6: MI-05 | C6: Price ceilings, floors and taxes: who really pays? | D6: McAfee & Lewis, Introduction to Economic Analysis (CC BY-NC-SA) §5 Government interventions | E6: Explainer | F6: 8-10 min | G6: MI-04 | H6: IB/A-level | I6: Medium | J6: Stale (median outlier age 8y+) | K6: 9
A7: Intermediate Microeconomics | B7: MI-06 | C7: Indifference curves and the budget constraint, visualised | D7: McAfee & Lewis, Introduction to Economic Analysis (CC BY-NC-SA) §12 Consumer Theory: utility | E7: Explainer | F7: 10-12 min | G7: MI-01 | H7: University | I7: High | J7: Stale (median outlier age 8y+) | K7: 11
A8: Intermediate Microeconomics | B8: MI-07 | C8: Income vs substitution effects (the Slutsky decomposition, step by step) | D8: McAfee & Lewis, Introduction to Economic Analysis (CC BY-NC-SA) §12.3 Income & substitution effects | E8: Explainer | F8: 10-12 min | G8: MI-06 | H8: University | I8: Medium | J8: Stale (median outlier age 8y+) | K8: 13
A9: Intermediate Microeconomics | B9: MI-08 | C9: Marginal utility and why demand slopes down | D9: McAfee & Lewis, Introduction to Economic Analysis (CC BY-NC-SA) §12.1 Marginal utility | E9: Explainer | F9: 6-8 min | G9: MI-06 | H9: IB/A-level | I9: High | J9: Stale (median outlier age 8y+) | K9: 19
A10: Intermediate Microeconomics | B10: MI-09 | C10: How to calculate marginal, average and total cost (and draw the curves) | D10: McAfee & Lewis, Introduction to Economic Analysis (CC BY-NC-SA) §9 Producer Theory: cost curves | E10: Worked problem ("how to solve") | F10: 8-10 min | G10: None | H10: IB/A-level/AP | I10: Medium | J10: Stale (median outlier age 8y+) | K10: 21
A11: Intermediate Microeconomics | B11: MI-10 | C11: Economies of scale and the long-run average cost curve | D11: McAfee & Lewis, Introduction to Economic Analysis (CC BY-NC-SA) §9.3 Returns to scale | E11: Explainer | F11: 6-8 min | G11: MI-09 | H11: IB/A-level/AP | I11: High | J11: Stale (median outlier age 8y+) | K11: 23
A12: Intermediate Microeconomics | B12: MI-11 | C12: Cobb-Douglas: the production function that runs economics | D12: McAfee & Lewis, Introduction to Economic Analysis (CC BY-NC-SA) §9.1 Production functions | E12: Explainer | F12: 8-10 min | G12: MI-09 | H12: University | I12: High | J12: Stale (median outlier age 8y+) | K12: 25
A13: Intermediate Microeconomics | B13: MI-12 | C13: Perfect competition: profit maximisation and the shutdown rule | D13: McAfee & Lewis, Introduction to Economic Analysis (CC BY-NC-SA) §10 Perfect competition | E13: Explainer | F13: 10-12 min | G13: MI-09 | H13: IB/A-level/AP | I13: High | J13: Ageing (4-8y) | K13: 30
... A101: Cross-course | B101: XC-04 | C101: Every IB Economics diagram in 15 minutes | D101: Exam funnel | E101: Anchor (ALL of…) | F101: 15 min | G101: MI-01…MA-18 | H101: IB | I101: High | J101: Stale (median outlier age 8y+) | K101: 63

Sheet Progress
A1: Progress
A3: By status | D3: By course | E3: Videos | F3: Published | H3: By demand signal | I3: Videos | K3: By supply age | L3: Videos
A4: Planned | B4: =COUNTIF(Backlog!$AB$2:$AB$101,A4) -> 100 | D4: Intermediate Microeconomics | E4: =COUNTIF(Backlog!$E$2:$E$101,D4) -> 30 | F4: =COUNTIFS(Backlog!$E$2:$E$101,D4,Backlog!$AB$2:$AB$101,"Published") -> 0 | H4: High | I4: =COUNTIF(Backlog!$L$2:$L$101,H4) -> 36 | K4: Stale (median outlier age 8y+) | L4: =COUNTIF(Backlog!$M$2:$M$101,K4) -> 52
A5: Scripted | B5: =COUNTIF(Backlog!$AB$2:$AB$101,A5) -> 0 | D5: Intermediate Macroeconomics | E5: =COUNTIF(Backlog!$E$2:$E$101,D5) -> 26 | F5: =COUNTIFS(Backlog!$E$2:$E$101,D5,Backlog!$AB$2:$AB$101,"Published") -> 0 | H5: Medium | I5: =COUNTIF(Backlog!$L$2:$L$101,H5) -> 40 | K5: Ageing (4-8y) | L5: =COUNTIF(Backlog!$M$2:$M$101,K5) -> 17
A6: Audio done | B6: =COUNTIF(Backlog!$AB$2:$AB$101,A6) -> 0 | D6: Game Theory | E6: =COUNTIF(Backlog!$E$2:$E$101,D6) -> 14 | F6: =COUNTIFS(Backlog!$E$2:$E$101,D6,Backlog!$AB$2:$AB$101,"Published") -> 0 | H6: Low | I6: =COUNTIF(Backlog!$L$2:$L$101,H6) -> 20 | K6: Fresh (<4y) | L6: =COUNTIF(Backlog!$M$2:$M$101,K6) -> 7
A7: Rendered | B7: =COUNTIF(Backlog!$AB$2:$AB$101,A7) -> 0 | D7: Econometrics | E7: =COUNTIF(Backlog!$E$2:$E$101,D7) -> 26 | F7: =COUNTIFS(Backlog!$E$2:$E$101,D7,Backlog!$AB$2:$AB$101,"Published") -> 0 | H7: No comparable video | I7: =COUNTIF(Backlog!$L$2:$L$101,H7) -> 4 | K7: - | L7: =COUNTIF(Backlog!$M$2:$M$101,K7) -> 24
A8: Published | B8: =COUNTIF(Backlog!$AB$2:$AB$101,A8) -> 0 | D8: Cross-course | E8: =COUNTIF(Backlog!$E$2:$E$101,D8) -> 4 | F8: =COUNTIFS(Backlog!$E$2:$E$101,D8,Backlog!$AB$2:$AB$101,"Published") -> 0
A9: Total | B9: =SUM(B4:B8) -> 100
A12: Next up (first 5 not yet published)
A13: =IFERROR(INDEX(Backlog!$D$2:$D$101,MATCH(1,Backlog!$AE$2:$AE$101,0)),"") -> MI-01 | B13: =IFERROR(INDEX(Backlog!$G$2:$G$101,MATCH(1,Backlog!$AE$2:$AE$101,0)),"") -> Supply and demand, properly: what shifts a curve and what moves along it
A14: =IFERROR(INDEX(Backlog!$D$2:$D$101,MATCH(2,Backlog!$AE$2:$AE$101,0)),"") -> MA-01 | B14: =IFERROR(INDEX(Backlog!$G$2:$G$101,MATCH(2,Backlog!$AE$2:$AE$101,0)),"") -> GDP, properly: three ways to measure one number
A15: =IFERROR(INDEX(Backlog!$D$2:$D$101,MATCH(3,Backlog!$AE$2:$AE$101,0)),"") -> MI-02 | B15: =IFERROR(INDEX(Backlog!$G$2:$G$101,MATCH(3,Backlog!$AE$2:$AE$101,0)),"") -> How to solve elasticity problems (point, arc, revenue test)
A16: =IFERROR(INDEX(Backlog!$D$2:$D$101,MATCH(4,Backlog!$AE$2:$AE$101,0)),"") -> MA-02 | B16: =IFERROR(INDEX(Backlog!$G$2:$G$101,MATCH(4,Backlog!$AE$2:$AE$101,0)),"") -> Inflation, the CPI and the GDP deflator (and why they disagree)
A17: =IFERROR(INDEX(Backlog!$D$2:$D$101,MATCH(5,Backlog!$AE$2:$AE$101,0)),"") -> MI-03 | B17: =IFERROR(INDEX(Backlog!$G$2:$G$101,MATCH(5,Backlog!$AE$2:$AE$101,0)),"") -> How to calculate opportunity cost (and why the PPF is curved)
